Workbook
Name Slicer_Payment_Method: #N/A
Name Slicer_Product_Category: #N/A
Name Slicer_Region: #N/A

Sheet Sheet1
A3: Sum of Total Amount | B3: Column Labels
A4: Row Labels | B4: Books | C4: Electronics | D4: Fashion | E4: Home | F4: Toys | G4: Grand Total
A5: Central | B5: 84 | C5: 2662 | D5: 210 | E5: 2063 | F5: 437 | G5: 5456
A6: East | B6: 394 | C6: 365 | D6: 711 | E6: 741 | F6: 1424 | G6: 3635
A7: North | B7: 464 | C7: 6522 | D7: 788 | E7: 2131 | F7: 586 | G7: 10491
A8: South | B8: 423 | C8: 3938 | D8: 1032 | E8: 1881 | F8: 43 | G8: 7317
A9: West | B9: 350 | C9: 1722 | D9: 1131 | E9: 4135 | F9: 1021 | G9: 8359
A10: Grand Total | B10: 1715 | C10: 15209 | D10: 3872 | E10: 10951 | F10: 3511 | G10: 35258

Sheet Sheet2
A3: Row Labels | B3: Count of Order ID
A4: Cancelled | B4: 30
A5: Delivered | B5: 34
A6: In Transit | B6: 36
A7: Grand Total | B7: 100

Sheet Sheet3
A3: Row Labels | B3: Average of Delivery Time
A4: Central | B4: 4.2
A5: East | B5: 4.25
A6: North | B6: 3.625
A7: South | B7: 3.3333333
A8: West | B8: 3.4285714
A9: Grand Total | B9: 3.7647059

Sheet Sheet4
A3: Count of Order ID | B3: Column Labels
A4: Row Labels | B4: Cancelled | C4: Delivered | D4: Grand Total | E4: Cancellation Rate
A5: Central | B5: 5 | C5: 9 | D5: 14 | E5: =B5/D5 -> 0.35714286
A6: East | B6: 3 | C6: 15 | D6: 18 | E6: =B6/D6 -> 0.16666667
A7: North | B7: 10 | C7: 15 | D7: 25 | E7: =B7/D7 -> 0.4
A8: South | B8: 4 | C8: 16 | D8: 20 | E8: =B8/D8 -> 0.2
A9: West | B9: 8 | C9: 15 | D9: 23 | E9: =B9/D9 -> 0.34782609
A10: Grand Total | B10: 30 | C10: 70 | D10: 100 | E10: =B10/D10 -> 0.3

Sheet Sheet6
A3: Sum of Effective Sales
A4: 3010

Sheet sales by region
A3: Row Labels | B3: Sum of Total Amount
A4: Central | B4: 5456
A5: Grand Total | B5: 5456

Sheet sale by product catagory
A3: Row Labels | B3: Sum of Total Amount
A4: Books | B4: 84
A5: Electronics | B5: 2662
A6: Fashion | B6: 210
A7: Home | B7: 2063
A8: Toys | B8: 437
A9: Grand Total | B9: 5456

Sheet order by delivery status
A3: Row Labels | B3: Count of Order ID
A4: Cancelled | B4: 5
A5: Delivered | B5: 5
A6: In Transit | B6: 4
A7: Grand Total | B7: 14

Sheet Sheet12
W17: Sum of Total Amount
W18: 5456
W20: =Sheet17!C5 -> 0.071428571
W22: Electronics
W28: North

Sheet Sheet14
A3: Row Labels | B3: Sum of Total Amount
A4: Central | B4: 5456
A5: Grand Total | B5: 5456

Sheet Sheet15
A3: Row Labels | B3: Sum of Total Amount
A4: Books | B4: 84
A5: Electronics | B5: 2662
A6: Fashion | B6: 210
A7: Home | B7: 2063
A8: Toys | B8: 437
A9: Grand Total | B9: 5456

Sheet Sheet16
A3: Sum of Total Amount
A4: 5456

Sheet Sheet17
A3: Row Labels | B3: Count of Order ID
A4: Cancelled | B4: 9
A5: Fast | B5: 1 | C5: =B5/B7 -> 0.071428571
A6: Slow | B6: 4
A7: Grand Total | B7: 14

Sheet Orders
A1: Order ID | B1: Customer ID | C1: Product ID | D1: Region | E1: Sale Price/Unit | F1: Quantity | G1: Total Amount | H1: Payment Method | I1: Delivery Status | J1: Fulfillment Partner | K1: Order Date | L1: Delivery Date | M1: Cancel Date | N1: Order Status | O1: Delivery Time | P1: Delivery Performance | Q1: Customer Name | R1: Product Category | S1: Product Name | T1: Effective Sales
A2: ORD0001 | B2: CUST021 | C2: PROD012 | D2: North | E2: 44 | F2: 1 | G2: 44 | H2: Apple Pay | I2: Cancelled | J2: DHL | K2: 45291 | M2: 45293 | N2: =IF(M2<>"","Cancelled","Delivered") -> Cancelled | O2: =IF(L2<>"",L2-K2,"NA") -> NA | P2: =IF(L2="","Cancelled",IF(L2-K2<=2,"Fast","Slow")) -> Cancelled | Q2: =_xlfn.XLOOKUP(Orders!B2,'Customer Master'!$A$1:$A$50,'Customer Master'!$B$1:$B$50) -> Zoe Mitchell | R2: =_xlfn.XLOOKUP(Orders!C2,'Product Master'!$A$1:$A$23,'Product Master'!$C$1:$C$23) -> Home | S2: =_xlfn.XLOOKUP(C2,'Product Master'!$A$1:$A$23,'Product Master'!$B$1:$B$23) -> Lamp | T2: =IF(I2="Delivered",G2,0) -> 0
A3: ORD0002 | B3: CUST029 | C3: PROD018 | D3: East | E3: 96 | F3: 4 | G3: 384 | H3: Credit Card | I3: Delivered | J3: DHL | K3: 44979 | L3: 44981 | N3: =IF(M3<>"","Cancelled","Delivered") -> Delivered | O3: =IF(L3<>"",L3-K3,"NA") -> 2 | P3: =IF(L3="","Cancelled",IF(L3-K3<=2,"Fast","Slow")) -> Fast | Q3: =_xlfn.XLOOKUP(Orders!B3,'Customer Master'!$A$1:$A$50,'Customer Master'!$B$1:$B$50) -> Ava White | R3: =_xlfn.XLOOKUP(Orders!C3,'Product Master'!$A$1:$A$23,'Product Master'!$C$1:$C$23) -> Toys | S3: =_xlfn.XLOOKUP(C3,'Product Master'!$A$1:$A$23,'Product Master'!$B$1:$B$23) -> Doll House | T3: =IF(I3="Delivered",G3,0) -> 384
A4: ORD0003 | B4: CUST021 | C4: PROD013 | D4: South | E4: 194 | F4: 4 | G4: 776 | H4: Credit Card | I4: In Transit | J4: USPS | K4: 45210 | N4: =IF(M4<>"","Cancelled","Delivered") -> Delivered | O4: =IF(L4<>"",L4-K4,"NA") -> NA | P4: =IF(L4="","Cancelled",IF(L4-K4<=2,"Fast","Slow")) -> Cancelled | Q4: =_xlfn.XLOOKUP(Orders!B4,'Customer Master'!$A$1:$A$50,'Customer Master'!$B$1:$B$50) -> Zoe Mitchell | R4: =_xlfn.XLOOKUP(Orders!C4,'Product Master'!$A$1:$A$23,'Product Master'!$C$1:$C$23) -> Home | S4: =_xlfn.XLOOKUP(C4,'Product Master'!$A$1:$A$23,'Product Master'!$B$1:$B$23) -> Vacuum Cleaner | T4: =IF(I4="Delivered",G4,0) -> 0
A5: ORD0004 | B5: CUST044 | C5: PROD013 | D5: North | E5: 196 | F5: 3 | G5: 588 | H5: PayPal | I5: Cancelled | J5: UPS | K5: 45051 | M5: 45057 | N5: =IF(M5<>"","Cancelled","Delivered") -> Cancelled | O5: =IF(L5<>"",L5-K5,"NA") -> NA | P5: =IF(L5="","Cancelled",IF(L5-K5<=2,"Fast","Slow")) -> Cancelled | Q5: =_xlfn.XLOOKUP(Orders!B5,'Customer Master'!$A$1:$A$50,'Customer Master'!$B$1:$B$50) -> Grace Ward | R5: =_xlfn.XLOOKUP(Orders!C5,'Product Master'!$A$1:$A$23,'Product Master'!$C$1:$C$23) -> Home | S5: =_xlfn.XLOOKUP(C5,'Product Master'!$A$1:$A$23,'Product Master'!$B$1:$B$23) -> Vacuum Cleaner | T5: =IF(I5="Delivered",G5,0) -> 0
A6: ORD0005 | B6: CUST027 | C6: PROD010 | D6: North | E6: 59 | F6: 1 | G6: 59 | H6: PayPal | I6: Delivered | J6: Amazon Logistics | K6: 44959 | L6: 44962 | N6: =IF(M6<>"","Cancelled","Delivered") -> Delivered | O6: =IF(L6<>"",L6-K6,"NA") -> 3 | P6: =IF(L6="","Cancelled",IF(L6-K6<=2,"Fast","Slow")) -> Slow | Q6: =_xlfn.XLOOKUP(Orders!B6,'Customer Master'!$A$1:$A$50,'Customer Master'!$B$1:$B$50) -> Hazel Brooks | R6: =_xlfn.XLOOKUP(Orders!C6,'Product Master'!$A$1:$A$23,'Product Master'!$C$1:$C$23) -> Fashion | S6: =_xlfn.XLOOKUP(C6,'Product Master'!$A$1:$A$23,'Product Master'!$B$1:$B$23) -> Jeans | T6: =IF(I6="Delivered",G6,0) -> 59
A7: ORD0006 | B7: CUST009 | C7: PROD010 | D7: North | E7: 58 | F7: 4 | G7: 232 | H7: Amazon Pay | I7: Cancelled | J7: DHL | K7: 45231 | M7: 45232 | N7: =IF(M7<>"","Cancelled","Delivered") -> Cancelled | O7: =IF(L7<>"",L7-K7,"NA") -> NA | P7: =IF(L7="","Cancelled",IF(L7-K7<=2,"Fast","Slow")) -> Cancelled | Q7: =_xlfn.XLOOKUP(Orders!B7,'Customer Master'!$A$1:$A$50,'Customer Master'!$B$1:$B$50) -> Jackson Allen | R7: =_xlfn.XLOOKUP(Orders!C7,'Product Master'!$A$1:$A$23,'Product Master'!$C$1:$C$23) -> Fashion | S7: =_xlfn.XLOOKUP(C7,'Product Master'!$A$1:$A$23,'Product Master'!$B$1:$B$23) -> Jeans | T7: =IF(I7="Delivered",G7,0) -> 0
A8: ORD0007 | B8: CUST042 | C8: PROD020 | D8: Central | E8: 105 | F8: 3 | G8: 315 | H8: Debit Card | I8: Cancelled | J8: DHL | K8: 45152 | M8: 45156 | N8: =IF(M8<>"","Cancelled","Delivered") -> Cancelled | O8: =IF(L8<>"",L8-K8,"NA") -> NA | P8: =IF(L8="","Cancelled",IF(L8-K8<=2,"Fast","Slow")) -> Cancelled | Q8: =_xlfn.XLOOKUP(Orders!B8,'Customer Master'!$A$1:$A$50,'Customer Master'!$B$1:$B$50) -> Noah Wilson | R8: =_xlfn.XLOOKUP(Orders!C8,'Product Master'!$A$1:$A$23,'Product Master'!$C$1:$C$23) -> Electronics | S8: =_xlfn.XLOOKUP(C8,'Product Master'!$A$1:$A$23,'Product Master'!$B$1:$B$23) -> Bluetooth Speaker | T8: =IF(I8="Delivered",G8,0) -> 0
A9: ORD0008 | B9: CUST019 | C9: PROD021 | D9: West | E9: 37 | F9: 5 | G9: 185 | H9: PayPal | I9: Cancelled | J9: DHL | K9: 45017 | M9: 45022 | N9: =IF(M9<>"","Cancelled","Delivered") -> Cancelled | O9: =IF(L9<>"",L9-K9,"NA") -> NA | P9: =IF(L9="","Cancelled",IF(L9-K9<=2,"Fast","Slow")) -> Cancelled | Q9: =_xlfn.XLOOKUP(Orders!B9,'Customer Master'!$A$1:$A$50,'Customer Master'!$B$1:$B$50) -> Ava Robinson | R9: =_xlfn.XLOOKUP(Orders!C9,'Product Master'!$A$1:$A$23,'Product Master'!$C$1:$C$23) -> Home | S9: =_xlfn.XLOOKUP(C9,'Product Master'!$A$1:$A$23,'Product Master'!$B$1:$B$23) -> Wall Clock | T9: =IF(I9="Delivered",G9,0) -> 0
A10: ORD0009 | B10: CUST013 | C10: PROD019 | D10: Central | E10: 44 | F10: 2 | G10: 88 | H10: Credit Card | I10: In Transit | J10: Amazon Logistics | K10: 45128 | N10: =IF(M10<>"","Cancelled","Delivered") -> Delivered | O10: =IF(L10<>"",L10-K10,"NA") -> NA | P10: =IF(L10="","Cancelled",IF(L10-K10<=2,"Fast","Slow")) -> Cancelled | Q10: =_xlfn.XLOOKUP(Orders!B10,'Customer Master'!$A$1:$A$50,'Customer Master'!$B$1:$B$50) -> Olivia Martinez | R10: =_xlfn.XLOOKUP(Orders!C10,'Product Master'!$A$1:$A$23,'Product Master'!$C$1:$C$23) -> Fashion | S10: =_xlfn.XLOOKUP(C10,'Product Master'!$A$1:$A$23,'Product Master'!$B$1:$B$23) -> Formal Shirt | T10: =IF(I10="Delivered",G10,0) -> 0
A11: ORD0010 | B11: CUST019 | C11: PROD003 | D11: South | E11: 141 | F11: 4 | G11: 564 | H11: Debit Card | I11: In Transit | J11: DHL | K11: 45289 | N11: =IF(M11<>"","Cancelled","Delivered") -> Delivered | O11: =IF(L11<>"",L11-K11,"NA") -> NA | P11: =IF(L11="","Cancelled",IF(L11-K11<=2,"Fast","Slow")) -> Cancelled | Q11: =_xlfn.XLOOKUP(Orders!B11,'Customer Master'!$A$1:$A$50,'Customer Master'!$B$1:$B$50) -> Ava Robinson | R11: =_xlfn.XLOOKUP(Orders!C11,'Product Master'!$A$1:$A$23,'Product Master'!$C$1:$C$23) -> Home | S11: =_xlfn.XLOOKUP(C11,'Product Master'!$A$1:$A$23,'Product Master'!$B$1:$B$23) -> Cookware Set | T11: =IF(I11="Delivered",G11,0) -> 0
A12: ORD0011 | B12: CUST046 | C12: PROD014 | D12: South | E12: 249 | F12: 1 | G12: 249 | H12: Amazon Pay | I12: Cancelled | J12: USPS | K12: 45050 | M12: 45054 | N12: =IF(M12<>"","Cancelled","Delivered") -> Cancelled | O12: =IF(L12<>"",L12-K12,"NA") -> NA | P12: =IF(L12="","Cancelled",IF(L12-K12<=2,"Fast","Slow")) -> Cancelled | Q12: =_xlfn.XLOOKUP(Orders!B12,'Customer Master'!$A$1:$A$50,'Customer Master'!$B$1:$B$50) -> Emily Johnson | R12: =_xlfn.XLOOKUP(Orders!C12,'Product Master'!$A$1:$A$23,'Product Master'!$C$1:$C$23) -> Electronics | S12: =_xlfn.XLOOKUP(C12,'Product Master'!$A$1:$A$23,'Product Master'!$B$1:$B$23) -> Smartwatch | T12: =IF(I12="Delivered",G12,0) -> 0
A13: ORD0012 | B13: CUST045 | C13: PROD014 | D13: Central | E13: 247 | F13: 3 | G13: 741 | H13: Amazon Pay | I13: In Transit | J13: FedEx | K13: 45132 | N13: =IF(M13<>"","Cancelled","Delivered") -> Delivered | O13: =IF(L13<>"",L13-K13,"NA") -> NA | P13: =IF(L13="","Cancelled",IF(L13-K13<=2,"Fast","Slow")) -> Cancelled | Q13: =_xlfn.XLOOKUP(Orders!B13,'Customer Master'!$A$1:$A$50,'Customer Master'!$B$1:$B$50) -> Emily Johnson | R13: =_xlfn.XLOOKUP(Orders!C13,'Product Master'!$A$1:$A$23,'Product Master'!$C$1:$C$23) -> Electronics | S13: =_xlfn.XLOOKUP(C13,'Product Master'!$A$1:$A$23,'Product Master'!$B$1:$B$23) -> Smartwatch | T13: =IF(I13="Delivered",G13,0) -> 0
A14: ORD0013 | B14: CUST023 | C14: PROD006 | D14: Central | E14: 96 | F14: 1 | G14: 96 | H14: Apple Pay | I14: Cancelled | J14: Amazon Logistics | K14: 44982 | M14: 44985 | N14: =IF(M14<>"","Cancelled","Delivered") -> Cancelled | O14: =IF(L14<>"",L14-K14,"NA") -> NA | P14: =IF(L14="","Cancelled",IF(L14-K14<=2,"Fast","Slow")) -> Cancelled | Q14: =_xlfn.XLOOKUP(Orders!B14,'Customer Master'!$A$1:$A$50,'Customer Master'!$B$1:$B$50) -> Charlotte Reed | R14: =_xlfn.XLOOKUP(Orders!C14,'Product Master'!$A$1:$A$23,'Product Master'!$C$1:$C$23) -> Fashion | S14: =_xlfn.XLOOKUP(C14,'Product Master'!$A$1:$A$23,'Product Master'!$B$1:$B$23) -> Shoes | T14: =IF(I14="Delivered",G14,0) -> 0
A15: ORD0014 | B15: CUST033 | C15: PROD017 | D15: West | E15: 74 | F15: 5 | G15: 370 | H15: Apple Pay | I15: Cancelled | J15: Amazon Logistics | K15: 44981 | M15: 44982 | N15: =IF(M15<>"","Cancelled","Delivered") -> Cancelled | O15: =IF(L15<>"",L15-K15,"NA") -> NA | P15: =IF(L15="","Cancelled",IF(L15-K15<=2,"Fast","Slow")) -> Cancelled | Q15: =_xlfn.XLOOKUP(Orders!B15,'Customer Master'!$A$1:$A$50,'Customer Master'!$B$1:$B$50) -> Hazel Rivera | R15: =_xlfn.XLOOKUP(Orders!C15,'Product Master'!$A$1:$A$23,'Product Master'!$C$1:$C$23) -> Electronics | S15: =_xlfn.XLOOKUP(C15,'Product Master'!$A$1:$A$23,'Product Master'!$B$1:$B$23) -> Gaming Mouse | T15: =IF(I15="Delivered",G15,0) -> 0
A16: ORD0015 | B16: CUST033 | C16: PROD005 | D16: South | E16: 27 | F16: 1 | G16: 27 | H16: Credit Card | I16: Cancelled | J16: Amazon Logistics | K16: 45164 | M16: 45171 | N16: =IF(M16<>"","Cancelled","Delivered") -> Cancelled | O16: =IF(L16<>"",L16-K16,"NA") -> NA | P16: =IF(L16="","Cancelled",IF(L16-K16<=2,"Fast","Slow")) -> Cancelled | Q16: =_xlfn.XLOOKUP(Orders!B16,'Customer Master'!$A$1:$A$50,'Customer Master'!$B$1:$B$50) -> Hazel Rivera | R16: =_xlfn.XLOOKUP(Orders!C16,'Product Master'!$A$1:$A$23,'Product Master'!$C$1:$C$23) -> Fashion | S16: =_xlfn.XLOOKUP(C16,'Product Master'!$A$1:$A$23,'Product Master'!$B$1:$B$23) -> T-Shirt | T16: =IF(I16="Delivered",G16,0) -> 0
A17: ORD0016 | B17: CUST047 | C17: PROD005 | D17: South | E17: 27 | F17: 3 | G17: 81 | H17: Debit Card | I17: In Transit | J17: Amazon Logistics | K17: 44970 | N17: =IF(M17<>"","Cancelled","Delivered") -> Delivered | O17: =IF(L17<>"",L17-K17,"NA") -> NA | P17: =IF(L17="","Cancelled",IF(L17-K17<=2,"Fast","Slow")) -> Cancelled | Q17: =_xlfn.XLOOKUP(Orders!B17,'Customer Master'!$A$1:$A$50,'Customer Master'!$B$1:$B$50) -> Scarlett Murphy | R17: =_xlfn.XLOOKUP(Orders!C17,'Product Master'!$A$1:$A$23,'Product Master'!$C$1:$C$23) -> Fashion | S17: =_xlfn.XLOOKUP(C17,'Product Master'!$A$1:$A$23,'Product Master'!$B$1:$B$23) -> T-Shirt | T17: =IF(I17="Delivered",G17,0) -> 0
A18: ORD0017 | B18: CUST045 | C18: PROD015 | D18: East | E18: 21 | F18: 3 | G18: 63 | H18: Credit Card | I18: Delivered | J18: DHL | K18: 45105 | L18: 45108 | N18: =IF(M18<>"","Cancelled","Delivered") -> Delivered | O18: =IF(L18<>"",L18-K18,"NA") -> 3 | P18: =IF(L18="","Cancelled",IF(L18-K18<=2,"Fast","Slow")) -> Slow | Q18: =_xlfn.XLOOKUP(Orders!B18,'Customer Master'!$A$1:$A$50,'Customer Master'!$B$1:$B$50) -> Emily Johnson | R18: =_xlfn.XLOOKUP(Orders!C18,'Product Master'!$A$1:$A$23,'Product Master'!$C$1:$C$23) -> Books | S18: =_xlfn.XLOOKUP(C18,'Product Master'!$A$1:$A$23,'Product Master'!$B$1:$B$23) -> Novel | T18: =IF(I18="Delivered",G18,0) -> 63
A19: ORD0018 | B19: CUST011 | C19: PROD008 | D19: West | E19: 70 | F19: 5 | G19: 350 | H19: PayPal | I19: In Transit | J19: Amazon Logistics | K19: 45258 | N19: =IF(M19<>"","Cancelled","Delivered") -> Delivered | O19: =IF(L19<>"",L19-K19,"NA") -> NA | P19: =IF(L19="","Cancelled",IF(L19-K19<=2,"Fast","Slow")) -> Cancelled | Q19: =_xlfn.XLOOKUP(Orders!B19,'Customer Master'!$A$1:$A$50,'Customer Master'!$B$1:$B$50) -> Mason Hall | R19: =_xlfn.XLOOKUP(Orders!C19,'Product Master'!$A$1:$A$23,'Product Master'!$C$1:$C$23) -> Books | S19: =_xlfn.XLOOKUP(C19,'Product Master'!$A$1:$A$23,'Product Master'!$B$1:$B$23) -> Textbook | T19: =IF(I19="Delivered",G19,0) -> 0
A20: ORD0019 | B20: CUST041 | C20: PROD006 | D20: South | E20: 94 | F20: 4 | G20: 376 | H20: Credit Card | I20: In Transit | J20: USPS | K20: 45163 | N20: =IF(M20<>"","Cancelled","Delivered") -> Delivered | O20: =IF(L20<>"",L20-K20,"NA") -> NA | P20: =IF(L20="","Cancelled",IF(L20-K20<=2,"Fast","Slow")) -> Cancelled | Q20: =_xlfn.XLOOKUP(Orders!B20,'Customer Master'!$A$1:$A$50,'Customer Master'!$B$1:$B$50) -> Jacob Price | R20: =_xlfn.XLOOKUP(Orders!C20,'Product Master'!$A$1:$A$23,'Product Master'!$C$1:$C$23) -> Fashion | S20: =_xlfn.XLOOKUP(C20,'Product Master'!$A$1:$A$23,'Product Master'!$B$1:$B$23) -> Shoes | T20: =IF(I20="Delivered",G20,0) -> 0
A21: ORD0020 | B21: CUST025 | C21: PROD001 | D21: North | E21: 813 | F21: 2 | G21: 1626 | H21: Credit Card | I21: In Transit | J21: FedEx | K21: 45028 | N21: =IF(M21<>"","Cancelled","Delivered") -> Delivered | O21: =IF(L21<>"",L21-K21,"NA") -> NA | P21: =IF(L21="","Cancelled",IF(L21-K21<=2,"Fast","Slow")) -> Cancelled | Q21: =_xlfn.XLOOKUP(Orders!B21,'Customer Master'!$A$1:$A$50,'Customer Master'!$B$1:$B$50) -> Emma King | R21: =_xlfn.XLOOKUP(Orders!C21,'Product Master'!$A$1:$A$23,'Product Master'!$C$1:$C$23) -> Electronics | S21: =_xlfn.XLOOKUP(C21,'Product Master'!$A$1:$A$23,'Product Master'!$B$1:$B$23) -> Smartphone | T21: =IF(I21="Delivered",G21,0) -> 0
A22: ORD0021 | B22: CUST013 | C22: PROD015 | D22: Central | E22: 21 | F22: 4 | G22: 84 | H22: PayPal | I22: In Transit | J22: Amazon Logistics | K22: 45201 | N22: =IF(M22<>"","Cancelled","Delivered") -> Delivered | O22: =IF(L22<>"",L22-K22,"NA") -> NA | P22: =IF(L22="","Cancelled",IF(L22-K22<=2,"Fast","Slow")) -> Cancelled | Q22: =_xlfn.XLOOKUP(Orders!B22,'Customer Master'!$A$1:$A$50,'Customer Master'!$B$1:$B$50) -> Olivia Martinez | R22: =_xlfn.XLOOKUP(Orders!C22,'Product Master'!$A$1:$A$23,'Product Master'!$C$1:$C$23) -> Books | S22: =_xlfn.XLOOKUP(C22,'Product Master'!$A$1:$A$23,'Product Master'!$B$1:$B$23) -> Novel | T22: =IF(I22="Delivered",G22,0) -> 0
A23: ORD0022 | B23: CUST023 | C23: PROD012 | D23: West | E23: 46 | F23: 5 | G23: 230 | H23: PayPal | I23: In Transit | J23: USPS | K23: 45239 | N23: =IF(M23<>"","Cancelled","Delivered") -> Delivered | O23: =IF(L23<>"",L23-K23,"NA") -> NA | P23: =IF(L23="","Cancelled",IF(L23-K23<=2,"Fast","Slow")) -> Cancelled | Q23: =_xlfn.XLOOKUP(Orders!B23,'Customer Master'!$A$1:$A$50,'Customer Master'!$B$1:$B$50) -> Charlotte Reed | R23: =_xlfn.XLOOKUP(Orders!C23,'Product Master'!$A$1:$A$23,'Product Master'!$C$1:$C$23) -> Home | S23: =_xlfn.XLOOKUP(C23,'Product Master'!$A$1:$A$23,'Product Master'!$B$1:$B$23) -> Lamp | T23: =IF(I23="Delivered",G23,0) -> 0
A24: ORD0023 | B24: CUST016 | C24: PROD010 | D24: West | E24: 58 | F24: 3 | G24: 174 | H24: Amazon Pay | I24: Cancelled | J24: Amazon Logistics | K24: 44970 | M24: 44971 | N24: =IF(M24<>"","Cancelled","Delivered") -> Cancelled | O24: =IF(L24<>"",L24-K24,"NA") -> NA | P24: =IF(L24="","Cancelled",IF(L24-K24<=2,"Fast","Slow")) -> Cancelled | Q24: =_xlfn.XLOOKUP(Orders!B24,'Customer Master'!$A$1:$A$50,'Customer Master'!$B$1:$B$50) -> Elijah Lewis | R24: =_xlfn.XLOOKUP(Orders!C24,'Product Master'!$A$1:$A$23,'Product Master'!$C$1:$C$23) -> Fashion | S24: =_xlfn.XLOOKUP(C24,'Product Master'!$A$1:$A$23,'Product Master'!$B$1:$B$23) -> Jeans | T24: =IF(I24="Delivered",G24,0) -> 0
A25: ORD0024 | B25: CUST028 | C25: PROD006 | D25: West | E25: 96 | F25: 5 | G25: 480 | H25: Amazon Pay | I25: Delivered | J25: Amazon Logistics | K25: 45232 | L25: 45235 | N25: =IF(M25<>"","Cancelled","Delivered") -> Delivered | O25: =IF(L25<>"",L25-K25,"NA") -> 3 | P25: =IF(L25="","Cancelled",IF(L25-K25<=2,"Fast","Slow")) -> Slow | Q25: =_xlfn.XLOOKUP(Orders!B25,'Customer Master'!$A$1:$A$50,'Customer Master'!$B$1:$B$50) -> Lily Bennett | R25: =_xlfn.XLOOKUP(Orders!C25,'Product Master'!$A$1:$A$23,'Product Master'!$C$1:$C$23) -> Fashion | S25: =_xlfn.XLOOKUP(C25,'Product Master'!$A$1:$A$23,'Product Master'!$B$1:$B$23) -> Shoes | T25: =IF(I25="Delivered",G25,0) -> 480
A26: ORD0025 | B26: CUST040 | C26: PROD002 | D26: South | E26: 43 | F26: 1 | G26: 43 | H26: Debit Card | I26: Delivered | J26: Amazon Logistics | K26: 45074 | L26: 45076 | N26: =IF(M26<>"","Cancelled","Delivered") -> Delivered | O26: =IF(L26<>"",L26-K26,"NA") -> 2 | P26: =IF(L26="","Cancelled",IF(L26-K26<=2,"Fast","Slow")) -> Fast | Q26: =_xlfn.XLOOKUP(Orders!B26,'Customer Master'!$A$1:$A$50,'Customer Master'!$B$1:$B$50) -> Benjamin Clark | R26: =_xlfn.XLOOKUP(Orders!C26,'Product Master'!$A$1:$A$23,'Product Master'!$C$1:$C$23) -> Toys | S26: =_xlfn.XLOOKUP(C26,'Product Master'!$A$1:$A$23,'Product Master'!$B$1:$B$23) -> Action Figure | T26: =IF(I26="Delivered",G26,0) -> 43
A27: ORD0026 | B27: CUST027 | C27: PROD022 | D27: South | E27: 64 | F27: 4 | G27: 256 | H27: Debit Card | I27: Delivered | J27: USPS | K27: 45214 | L27: 45220 | N27: =IF(M27<>"","Cancelled","Delivered") -> Delivered | O27: =IF(L27<>"",L27-K27,"NA") -> 6 | P27: =IF(L27="","Cancelled",IF(L27-K27<=2,"Fast","Slow")) -> Slow | Q27: =_xlfn.XLOOKUP(Orders!B27,'Customer Master'!$A$1:$A$50,'Customer Master'!$B$1:$B$50) -> Hazel Brooks | R27: =_xlfn.XLOOKUP(Orders!C27,'Product Master'!$A$1:$A$23,'Product Master'!$C$1:$C$23) -> Fashion | S27: =_xlfn.XLOOKUP(C27,'Product Master'!$A$1:$A$23,'Product Master'!$B$1:$B$23) -> Backpack | T27: =IF(I27="Delivered",G27,0) -> 256
A28: ORD0027 | B28: CUST018 | C28: PROD008 | D28: South | E28: 70 | F28: 2 | G28: 140 | H28: Amazon Pay | I28: In Transit | J28: Amazon Logistics | K28: 44942 | N28: =IF(M28<>"","Cancelled","Delivered") -> Delivered | O28: =IF(L28<>"",L28-K28,"NA") -> NA | P28: =IF(L28="","Cancelled",IF(L28-K28<=2,"Fast","Slow")) -> Cancelled | Q28: =_xlfn.XLOOKUP(Orders!B28,'Customer Master'!$A$1:$A$50,'Customer Master'!$B$1:$B$50) -> Grace Scott | R28: =_xlfn.XLOOKUP(Orders!C28,'Product Master'!$A$1:$A$23,'Product Master'!$C$1:$C$23) -> Books | S28: =_xlfn.XLOOKUP(C28,'Product Master'!$A$1:$A$23,'Product Master'!$B$1:$B$23) -> Textbook | T28: =IF(I28="Delivered",G28,0) -> 0
A29: ORD0028 | B29: CUST018 | C29: PROD018 | D29: Central | E29: 97 | F29: 3 | G29: 291 | H29: Credit Card | I29: In Transit | J29: Amazon Logistics | K29: 45208 | N29: =IF(M29<>"","Cancelled","Delivered") -> Delivered | O29: =IF(L29<>"",L29-K29,"NA") -> NA | P29: =IF(L29="","Cancelled",IF(L29-K29<=2,"Fast","Slow")) -> Cancelled | Q29: =_xlfn.XLOOKUP(Orders!B29,'Customer Master'!$A$1:$A$50,'Customer Master'!$B$1:$B$50) -> Grace Scott | R29: =_xlfn.XLOOKUP(Orders!C29,'Product Master'!$A$1:$A$23,'Product Master'!$C$1:$C$23) -> Toys | S29: =_xlfn.XLOOKUP(C29,'Product Master'!$A$1:$A$23,'Product Master'!$B$1:$B$23) -> Doll House | T29: =IF(I29="Delivered",G29,0) -> 0
A30: ORD0029 | B30: CUST007 | C30: PROD021 | D30: East | E30: 37 | F30: 3 | G30: 111 | H30: Apple Pay | I30: Cancelled | J30: DHL | K30: 45206 | M30: 45209 | N30: =IF(M30<>"","Cancelled","Delivered") -> Cancelled | O30: =IF(L30<>"",L30-K30,"NA") -> NA | P30: =IF(L30="","Cancelled",IF(L30-K30<=2,"Fast","Slow")) -> Cancelled | Q30: =_xlfn.XLOOKUP(Orders!B30,'Customer Master'!$A$1:$A$50,'Customer Master'!$B$1:$B$50) -> Liam Walker | R30: =_xlfn.XLOOKUP(Orders!C30,'Product Master'!$A$1:$A$23,'Product Master'!$C$1:$C$23) -> Home | S30: =_xlfn.XLOOKUP(C30,'Product Master'!$A$1:$A$23,'Product Master'!$B$1:$B$23) -> Wall Clock | T30: =IF(I30="Delivered",G30,0) -> 0
A31: ORD0030 | B31: CUST008 | C31: PROD008 | D31: North | E31: 69 | F31: 5 | G31: 345 | H31: Amazon Pay | I31: In Transit | J31: Amazon Logistics | K31: 44971 | N31: =IF(M31<>"","Cancelled","Delivered") -> Delivered | O31: =IF(L31<>"",L31-K31,"NA") -> NA | P31: =IF(L31="","Cancelled",IF(L31-K31<=2,"Fast","Slow")) -> Cancelled | Q31: =_xlfn.XLOOKUP(Orders!B31,'Customer Master'!$A$1:$A$50,'Customer Master'!$B$1:$B$50) -> Harper Young | R31: =_xlfn.XLOOKUP(Orders!C31,'Product Master'!$A$1:$A$23,'Product Master'!$C$1:$C$23) -> Books | S31: =_xlfn.XLOOKUP(C31,'Product Master'!$A$1:$A$23,'Product Master'!$B$1:$B$23) -> Textbook | T31: =IF(I31="Delivered",G31,0) -> 0
A32: ORD0031 | B32: CUST014 | C32: PROD002 | D32: North | E32: 42 | F32: 5 | G32: 210 | H32: Amazon Pay | I32: In Transit | J32: UPS | K32: 45011 | N32: =IF(M32<>"","Cancelled","Delivered") -> Delivered | O32: =IF(L32<>"",L32-K32,"NA") -> NA | P32: =IF(L32="","Cancelled",IF(L32-K32<=2,"Fast","Slow")) -> Cancelled | Q32: =_xlfn.XLOOKUP(Orders!B32,'Customer Master'!$A$1:$A$50,'Customer Master'!$B$1:$B$50) -> Harper Young | R32: =_xlfn.XLOOKUP(Orders!C32,'Product Master'!$A$1:$A$23,'Product Master'!$C$1:$C$23) -> Toys | S32: =_xlfn.XLOOKUP(C32,'Product Master'!$A$1:$A$23,'Product Master'!$B$1:$B$23) -> Action Figure | T32: =IF(I32="Delivered",G32,0) -> 0
A33: ORD0032 | B33: CUST037 | C33: PROD009 | D33: East | E33: 11 | F33: 5 | G33: 55 | H33: Debit Card | I33: Cancelled | J33: FedEx | K33: 45092 | M33: 45099 | N33: =IF(M33<>"","Cancelled","Delivered") -> Cancelled | O33: =IF(L33<>"",L33-K33,"NA") -> NA | P33: =IF(L33="","Cancelled",IF(L33-K33<=2,"Fast","Slow")) -> Cancelled | Q33: =_xlfn.XLOOKUP(Orders!B33,'Customer Master'!$A$1:$A$50,'Customer Master'!$B$1:$B$50) -> Emily Johnson | R33: =_xlfn.XLOOKUP(Orders!C33,'Product Master'!$A$1:$A$23,'Product Master'!$C$1:$C$23) -> Books | S33: =_xlfn.XLOOKUP(C33,'Product Master'!$A$1:$A$23,'Product Master'!$B$1:$B$23) -> Magazine | T33: =IF(I33="Delivered",G33,0) -> 0
A34: ORD0033 | B34: CUST016 | C34: PROD005 | D34: South | E34: 27 | F34: 2 | G34: 54 | H34: Apple Pay | I34: Delivered | J34: USPS | K34: 45068 | L34: 45069 | N34: =IF(M34<>"","Cancelled","Delivered") -> Delivered | O34: =IF(L34<>"",L34-K34,"NA") -> 1 | P34: =IF(L34="","Cancelled",IF(L34-K34<=2,"Fast","Slow")) -> Fast | Q34: =_xlfn.XLOOKUP(Orders!B34,'Customer Master'!$A$1:$A$50,'Customer Master'!$B$1:$B$50) -> Elijah Lewis | R34: =_xlfn.XLOOKUP(Orders!C34,'Product Master'!$A$1:$A$23,'Product Master'!$C$1:$C$23) -> Fashion | S34: =_xlfn.XLOOKUP(C34,'Product Master'!$A$1:$A$23,'Product Master'!$B$1:$B$23) -> T-Shirt | T34: =IF(I34="Delivered",G34,0) -> 54
A35: ORD0034 | B35: CUST025 | C35: PROD015 | D35: South | E35: 21 | F35: 1 | G35: 21 | H35: Amazon Pay | I35: In Transit | J35: DHL | K35: 45250 | N35: =IF(M35<>"","Cancelled","Delivered") -> Delivered | O35: =IF(L35<>"",L35-K35,"NA") -> NA | P35: =IF(L35="","Cancelled",IF(L35-K35<=2,"Fast","Slow")) -> Cancelled | Q35: =_xlfn.XLOOKUP(Orders!B35,'Customer Master'!$A$1:$A$50,'Customer Master'!$B$1:$B$50) -> Emma King | R35: =_xlfn.XLOOKUP(Orders!C35,'Product Master'!$A$1:$A$23,'Product Master'!$C$1:$C$23) -> Books | S35: =_xlfn.XLOOKUP(C35,'Product Master'!$A$1:$A$23,'Product Master'!$B$1:$B$23) -> Novel | T35: =IF(I35="Delivered",G35,0) -> 0
A36: ORD0035 | B36: CUST032 | C36: PROD011 | D36: South | E36: 172 | F36: 1 | G36: 172 | H36: PayPal | I36: Delivered | J36: USPS | K36: 45282 | L36: 45286 | N36: =IF(M36<>"","Cancelled","Delivered") -> Delivered | O36: =IF(L36<>"",L36-K36,"NA") -> 4 | P36: =IF(L36="","Cancelled",IF(L36-K36<=2,"Fast","Slow")) -> Slow | Q36: =_xlfn.XLOOKUP(Orders!B36,'Customer Master'!$A$1:$A$50,'Customer Master'!$B$1:$B$50) -> Luke Gray | R36: =_xlfn.XLOOKUP(Orders!C36,'Product Master'!$A$1:$A$23,'Product Master'!$C$1:$C$23) -> Electronics | S36: =_xlfn.XLOOKUP(C36,'Product Master'!$A$1:$A$23,'Product Master'!$B$1:$B$23) -> Headphones | T36: =IF(I36="Delivered",G36,0) -> 172
A37: ORD0036 | B37: CUST014 | C37: PROD016 | D37: North | E37: 212 | F37: 3 | G37: 636 | H37: Amazon Pay | I37: In Transit | J37: UPS | K37: 45130 | N37: =IF(M37<>"","Cancelled","Delivered") -> Delivered | O37: =IF(L37<>"",L37-K37,"NA") -> NA | P37: =IF(L37="","Cancelled",IF(L37-K37<=2,"Fast","Slow")) -> Cancelled | Q37: =_xlfn.XLOOKUP(Orders!B37,'Customer Master'!$A$1:$A$50,'Customer Master'!$B$1:$B$50) -> Harper Young | R37: =_xlfn.XLOOKUP(Orders!C37,'Product Master'!$A$1:$A$23,'Product Master'!$C$1:$C$23) -> Home | S37: =_xlfn.XLOOKUP(C37,'Product Master'!$A$1:$A$23,'Product Master'!$B$1:$B$23) -> Cookware Set Pro | T37: =IF(I37="Delivered",G37,0) -> 0
A38: ORD0037 | B38: CUST044 | C38: PROD002 | D38: East | E38: 41 | F38: 4 | G38: 164 | H38: Credit Card | I38: Delivered | J38: Amazon Logistics | K38: 45216 | L38: 45221 | N38: =IF(M38<>"","Cancelled","Delivered") -> Delivered | O38: =IF(L38<>"",L38-K38,"NA") -> 5 | P38: =IF(L38="","Cancelled",IF(L38-K38<=2,"Fast","Slow")) -> Slow | Q38: =_xlfn.XLOOKUP(Orders!B38,'Customer Master'!$A$1:$A$50,'Customer Master'!$B$1:$B$50) -> Grace Ward | R38: =_xlfn.XLOOKUP(Orders!C38,'Product Master'!$A$1:$A$23,'Product Master'!$C$1:$C$23) -> Toys | S38: =_xlfn.XLOOKUP(C38,'Product Master'!$A$1:$A$23,'Product Master'!$B$1:$B$23) -> Action Figure | T38: =IF(I38="Delivered",G38,0) -> 164
A39: ORD0038 | B39: CUST028 | C39: PROD007 | D39: North | E39: 32 | F39: 2 | G39: 64 | H39: Debit Card | I39: Cancelled | J39: FedEx | K39: 45160 | M39: 45162 | N39: =IF(M39<>"","Cancelled","Delivered") -> Cancelled | O39: =IF(L39<>"",L39-K39,"NA") -> NA | P39: =IF(L39="","Cancelled",IF(L39-K39<=2,"Fast","Slow")) -> Cancelled | Q39: =_xlfn.XLOOKUP(Orders!B39,'Customer Master'!$A$1:$A$50,'Customer Master'!$B$1:$B$50) -> Lily Bennett | R39: =_xlfn.XLOOKUP(Orders!C39,'Product Master'!$A$1:$A$23,'Product Master'!$C$1:$C$23) -> Toys | S39: =_xlfn.XLOOKUP(C39,'Product Master'!$A$1:$A$23,'Product Master'!$B$1:$B$23) -> Puzzle | T39: =IF(I39="Delivered",G39,0) -> 0
A40: ORD0039 | B40: CUST024 | C40: PROD022 | D40: East | E40: 66 | F40: 2 | G40: 132 | H40: Apple Pay | I40: In Transit | J40: DHL | K40: 45262 | N40: =IF(M40<>"","Cancelled","Delivered") -> Delivered | O40: =IF(L40<>"",L40-K40,"NA") -> NA | P40: =IF(L40="","Cancelled",IF(L40-K40<=2,"Fast","Slow")) -> Cancelled | Q40: =_xlfn.XLOOKUP(Orders!B40,'Customer Master'!$A$1:$A$50,'Customer Master'!$B$1:$B$50) -> Scarlett Murphy | R40: =_xlfn.XLOOKUP(Orders!C40,'Product Master'!$A$1:$A$23,'Product Master'!$C$1:$C$23) -> Fashion | S40: =_xlfn.XLOOKUP(C40,'Product Master'!$A$1:$A$23,'Product Master'!$B$1:$B$23) -> Backpack | T40: =IF(I40="Delivered",G40,0) -> 0
A41: ORD0040 | B41: CUST006 | C41: PROD004 | D41: East | E41: 62 | F41: 4 | G41: 248 | H41: Debit Card | I41: In Transit | J41: UPS | K41: 45285 | N41: =IF(M41<>"","Cancelled","Delivered") -> Delivered | O41: =IF(L41<>"",L41-K41,"NA") -> NA | P41: =IF(L41="","Cancelled",IF(L41-K41<=2,"Fast","Slow")) -> Cancelled | Q41: =_xlfn.XLOOKUP(Orders!B41,'Customer Master'!$A$1:$A$50,'Customer Master'!$B$1:$B$50) -> Ava Robinson | R41: =_xlfn.XLOOKUP(Orders!C41,'Product Master'!$A$1:$A$23,'Product Master'!$C$1:$C$23) -> Toys | S41: =_xlfn.XLOOKUP(C41,'Product Master'!$A$1:$A$23,'Product Master'!$B$1:$B$23) -> Leg Set | T41: =IF(I41="Delivered",G41,0) -> 0
A42: ORD0041 | B42: CUST001 | C42: PROD011 | D42: West | E42: 173 | F42: 4 | G42: 692 | H42: Apple Pay | I42: Delivered | J42: UPS | K42: 45192 | L42: 45199 | N42: =IF(M42<>"","Cancelled","Delivered") -> Delivered | O42: =IF(L42<>"",L42-K42,"NA") -> 7 | P42: =IF(L42="","Cancelled",IF(L42-K42<=2,"Fast","Slow")) -> Slow | Q42: =_xlfn.XLOOKUP(Orders!B42,'Customer Master'!$A$1:$A$50,'Customer Master'!$B$1:$B$50) -> James Miller | R42: =_xlfn.XLOOKUP(Orders!C42,'Product Master'!$A$1:$A$23,'Product Master'!$C$1:$C$23) -> Electronics | S42: =_xlfn.XLOOKUP(C42,'Product Master'!$A$1:$A$23,'Product Master'!$B$1:$B$23) -> Headphones | T42: =IF(I42="Delivered",G42,0) -> 692
A43: ORD0042 | B43: CUST007 | C43: PROD004 | D43: West | E43: 63 | F43: 3 | G43: 189 | H43: Apple Pay | I43: Delivered | J43: UPS | K43: 45123 | L43: 45125 | N43: =IF(M43<>"","Cancelled","Delivered") -> Delivered | O43: =IF(L43<>"",L43-K43,"NA") -> 2 | P43: =IF(L43="","Cancelled",IF(L43-K43<=2,"Fast","Slow")) -> Fast | Q43: =_xlfn.XLOOKUP(Orders!B43,'Customer Master'!$A$1:$A$50,'Customer Master'!$B$1:$B$50) -> Liam Walker | R43: =_xlfn.XLOOKUP(Orders!C43,'Product Master'!$A$1:$A$23,'Product Master'!$C$1:$C$23) -> Toys | S43: =_xlfn.XLOOKUP(C43,'Product Master'!$A$1:$A$23,'Product Master'!$B$1:$B$23) -> Leg Set | T43: =IF(I43="Delivered",G43,0) -> 189
A44: ORD0043 | B44: CUST040 | C44: PROD021 | D44: West | E44: 36 | F44: 3 | G44: 108 | H44: Debit Card | I44: Cancelled | J44: USPS | K44: 44962 | M44: 44968 | N44: =IF(M44<>"","Cancelled","Delivered") -> Cancelled | O44: =IF(L44<>"",L44-K44,"NA") -> NA | P44: =IF(L44="","Cancelled",IF(L44-K44<=2,"Fast","Slow")) -> Cancelled | Q44: =_xlfn.XLOOKUP(Orders!B44,'Customer Master'!$A$1:$A$50,'Customer Master'!$B$1:$B$50) -> Benjamin Clark | R44: =_xlfn.XLOOKUP(Orders!C44,'Product Master'!$A$1:$A$23,'Product Master'!$C$1:$C$23) -> Home | S44: =_xlfn.XLOOKUP(C44,'Product Master'!$A$1:$A$23,'Product Master'!$B$1:$B$23) -> Wall Clock | T44: =IF(I44="Delivered",G44,0) -> 0
A45: ORD0044 | B45: CUST006 | C45: PROD004 | D45: Central | E45: 62 | F45: 1 | G45: 62 | H45: Apple Pay | I45: Cancelled | J45: Amazon Logistics | K45: 45278 | M45: 45283 | N45: =IF(M45<>"","Cancelled","Delivered") -> Cancelled | O45: =IF(L45<>"",L45-K45,"NA") -> NA | P45: =IF(L45="","Cancelled",IF(L45-K45<=2,"Fast","Slow")) -> Cancelled | Q45: =_xlfn.XLOOKUP(Orders!B45,'Customer Master'!$A$1:$A$50,'Customer Master'!$B$1:$B$50) -> Ava Robinson | R45: =_xlfn.XLOOKUP(Orders!C45,'Product Master'!$A$1:$A$23,'Product Master'!$C$1:$C$23) -> Toys | S45: =_xlfn.XLOOKUP(C45,'Product Master'!$A$1:$A$23,'Product Master'!$B$1:$B$23) -> Leg Set | T45: =IF(I45="Delivered",G45,0) -> 0
A46: ORD0045 | B46: CUST042 | C46: PROD003 | D46: Central | E46: 137 | F46: 5 | G46: 685 | H46: Amazon Pay | I46: Cancelled | J46: FedEx | K46: 45088 | M46: 45091 | N46: =IF(M46<>"","Cancelled","Delivered") -> Cancelled | O46: =IF(L46<>"",L46-K46,"NA") -> NA | P46: =IF(L46="","Cancelled",IF(L46-K46<=2,"Fast","Slow")) -> Cancelled | Q46: =_xlfn.XLOOKUP(Orders!B46,'Customer Master'!$A$1:$A$50,'Customer Master'!$B$1:$B$50) -> Noah Wilson | R46: =_xlfn.XLOOKUP(Orders!C46,'Product Master'!$A$1:$A$23,'Product Master'!$C$1:$C$23) -> Home | S46: =_xlfn.XLOOKUP(C46,'Product Master'!$A$1:$A$23,'Product Master'!$B$1:$B$23) -> Cookware Set | T46: =IF(I46="Delivered",G46,0) -> 0
A47: ORD0046 | B47: CUST039 | C47: PROD017 | D47: North | E47: 73 | F47: 4 | G47: 292 | H47: Credit Card | I47: Delivered | J47: Amazon Logistics | K47: 45264 | L47: 45268 | N47: =IF(M47<>"","Cancelled","Delivered") -> Delivered | O47: =IF(L47<>"",L47-K47,"NA") -> 4 | P47: =IF(L47="","Cancelled",IF(L47-K47<=2,"Fast","Slow")) -> Slow | Q47: =_xlfn.XLOOKUP(Orders!B47,'Customer Master'!$A$1:$A$50,'Customer Master'!$B$1:$B$50) -> Logan Ramirez | R47: =_xlfn.XLOOKUP(Orders!C47,'Product Master'!$A$1:$A$23,'Product Master'!$C$1:$C$23) -> Electronics | S47: =_xlfn.XLOOKUP(C47,'Product Master'!$A$1:$A$23,'Product Master'!$B$1:$B$23) -> Gaming Mouse | T47: =IF(I47="Delivered",G47,0) -> 292
A48: ORD0047 | B48: CUST041 | C48: PROD020 | D48: North | E48: 104 | F48: 1 | G48: 104 | H48: PayPal | I48: Delivered | J48: Amazon Logistics | K48: 45124 | L48: 45126 | N48: =IF(M48<>"","Cancelled","Delivered") -> Delivered | O48: =IF(L48<>"",L48-K48,"NA") -> 2 | P48: =IF(L48="","Cancelled",IF(L48-K48<=2,"Fast","Slow")) -> Fast | Q48: =_xlfn.XLOOKUP(Orders!B48,'Customer Master'!$A$1:$A$50,'Customer Master'!$B$1:$B$50) -> Jacob Price | R48: =_xlfn.XLOOKUP(Orders!C48,'Product Master'!$A$1:$A$23,'Product Master'!$C$1:$C$23) -> Electronics | S48: =_xlfn.XLOOKUP(C48,'Product Master'!$A$1:$A$23,'Product Master'!$B$1:$B$23) -> Bluetooth Speaker | T48: =IF(I48="Delivered",G48,0) -> 104
A49: ORD0048 | B49: CUST044 | C49: PROD006 | D49: East | E49: 97 | F49: 1 | G49: 97 | H49: Amazon Pay | I49: Delivered | J49: FedEx | K49: 45218 | L49: 45223 | N49: =IF(M49<>"","Cancelled","Delivered") -> Delivered | O49: =IF(L49<>"",L49-K49,"NA") -> 5 | P49: =IF(L49="","Cancelled",IF(L49-K49<=2,"Fast","Slow")) -> Slow | Q49: =_xlfn.XLOOKUP(Orders!B49,'Customer Master'!$A$1:$A$50,'Customer Master'!$B$1:$B$50) -> Grace Ward | R49: =_xlfn.XLOOKUP(Orders!C49,'Product Master'!$A$1:$A$23,'Product Master'!$C$1:$C$23) -> Fashion | S49: =_xlfn.XLOOKUP(C49,'Product Master'!$A$1:$A$23,'Product Master'!$B$1:$B$23) -> Shoes | T49: =IF(I49="Delivered",G49,0) -> 97
A50: ORD0049 | B50: CUST026 | C50: PROD017 | D50: South | E50: 73 | F50: 5 | G50: 365 | H50: Apple Pay | I50: In Transit | J50: Amazon Logistics | K50: 45061 | N50: =IF(M50<>"","Cancelled","Delivered") -> Delivered | O50: =IF(L50<>"",L50-K50,"NA") -> NA | P50: =IF(L50="","Cancelled",IF(L50-K50<=2,"Fast","Slow")) -> Cancelled | Q50: =_xlfn.XLOOKUP(Orders!B50,'Customer Master'!$A$1:$A$50,'Customer Master'!$B$1:$B$50) -> Zoe Mitchell | R50: =_xlfn.XLOOKUP(Orders!C50,'Product Master'!$A$1:$A$23,'Product Master'!$C$1:$C$23) -> Electronics | S50: =_xlfn.XLOOKUP(C50,'Product Master'!$A$1:$A$23,'Product Master'!$B$1:$B$23) -> Gaming Mouse | T50: =IF(I50="Delivered",G50,0) -> 0
A51: ORD0050 | B51: CUST040 | C51: PROD005 | D51: East | E51: 27 | F51: 3 | G51: 81 | H51: Amazon Pay | I51: Delivered | J51: UPS | K51: 44969 | L51: 44976 | N51: =IF(M51<>"","Cancelled","Delivered") -> Delivered | O51: =IF(L51<>"",L51-K51,"NA") -> 7 | P51: =IF(L51="","Cancelled",IF(L51-K51<=2,"Fast","Slow")) -> Slow | Q51: =_xlfn.XLOOKUP(Orders!B51,'Customer Master'!$A$1:$A$50,'Customer Master'!$B$1:$B$50) -> Benjamin Clark | R51: =_xlfn.XLOOKUP(Orders!C51,'Product Master'!$A$1:$A$23,'Product Master'!$C$1:$C$23) -> Fashion | S51: =_xlfn.XLOOKUP(C51,'Product Master'!$A$1:$A$23,'Product Master'!$B$1:$B$23) -> T-Shirt | T51: =IF(I51="Delivered",G51,0) -> 81
A52: ORD0051 | B52: CUST041 | C52: PROD021 | D52: North | E52: 37 | F52: 1 | G52: 37 | H52: Apple Pay | I52: In Transit | J52: UPS | K52: 45201 | N52: =IF(M52<>"","Cancelled","Delivered") -> Delivered | O52: =IF(L52<>"",L52-K52,"NA") -> NA | P52: =IF(L52="","Cancelled",IF(L52-K52<=2,"Fast","Slow")) -> Cancelled | Q52: =_xlfn.XLOOKUP(Orders!B52,'Customer Master'!$A$1:$A$50,'Customer Master'!$B$1:$B$50) -> Jacob Price | R52: =_xlfn.XLOOKUP(Orders!C52,'Product Master'!$A$1:$A$23,'Product Master'!$C$1:$C$23) -> Home | S52: =_xlfn.XLOOKUP(C52,'Product Master'!$A$1:$A$23,'Product Master'!$B$1:$B$23) -> Wall Clock | T52: =IF(I52="Delivered",G52,0) -> 0
A53: ORD0052 | B53: CUST008 | C53: PROD015 | D53: North | E53: 22 | F53: 1 | G53: 22 | H53: Debit Card | I53: Delivered | J53: FedEx | K53: 44956 | L53: 44958 | N53: =IF(M53<>"","Cancelled","Delivered") -> Delivered | O53: =IF(L53<>"",L53-K53,"NA") -> 2 | P53: =IF(L53="","Cancelled",IF(L53-K53<=2,"Fast","Slow")) -> Fast | Q53: =_xlfn.XLOOKUP(Orders!B53,'Customer Master'!$A$1:$A$50,'Customer Master'!$B$1:$B$50) -> Harper Young | R53: =_xlfn.XLOOKUP(Orders!C53,'Product Master'!$A$1:$A$23,'Product Master'!$C$1:$C$23) -> Books | S53: =_xlfn.XLOOKUP(C53,'Product Master'!$A$1:$A$23,'Product Master'!$B$1:$B$23) -> Novel | T53: =IF(I53="Delivered",G53,0) -> 22
A54: ORD0053 | B54: CUST011 | C54: PROD016 | D54: Central | E54: 218 | F54: 5 | G54: 1090 | H54: PayPal | I54: Delivered | J54: DHL | K54: 45289 | L54: 45292 | N54: =IF(M54<>"","Cancelled","Delivered") -> Delivered | O54: =IF(L54<>"",L54-K54,"NA") -> 3 | P54: =IF(L54="","Cancelled",IF(L54-K54<=2,"Fast","Slow")) -> Slow | Q54: =_xlfn.XLOOKUP(Orders!B54,'Customer Master'!$A$1:$A$50,'Customer Master'!$B$1:$B$50) -> Mason Hall | R54: =_xlfn.XLOOKUP(Orders!C54,'Product Master'!$A$1:$A$23,'Product Master'!$C$1:$C$23) -> Home | S54: =_xlfn.XLOOKUP(C54,'Product Master'!$A$1:$A$23,'Product Master'!$B$1:$B$23) -> Cookware Set Pro | T54: =IF(I54="Delivered",G54,0) -> 1090
A55: ORD0054 | B55: CUST018 | C55: PROD004 | D55: North | E55: 64 | F55: 1 | G55: 64 | H55: Apple Pay | I55: Cancelled | J55: USPS | K55: 44991 | M55: 44998 | N55: =IF(M55<>"","Cancelled","Delivered") -> Cancelled | O55: =IF(L55<>"",L55-K55,"NA") -> NA | P55: =IF(L55="","Cancelled",IF(L55-K55<=2,"Fast","Slow")) -> Cancelled | Q55: =_xlfn.XLOOKUP(Orders!B55,'Customer Master'!$A$1:$A$50,'Customer Master'!$B$1:$B$50) -> Grace Scott | R55: =_xlfn.XLOOKUP(Orders!C55,'Product Master'!$A$1:$A$23,'Product Master'!$C$1:$C$23) -> Toys | S55: =_xlfn.XLOOKUP(C55,'Product Master'!$A$1:$A$23,'Product Master'!$B$1:$B$23) -> Leg Set | T55: =IF(I55="Delivered",G55,0) -> 0
A56: ORD0055 | B56: CUST037 | C56: PROD021 | D56: Central | E56: 36 | F56: 4 | G56: 144 | H56: PayPal | I56: Delivered | J56: Amazon Logistics | K56: 44959 | L56: 44963 | N56: =IF(M56<>"","Cancelled","Delivered") -> Delivered | O56: =IF(L56<>"",L56-K56,"NA") -> 4 | P56: =IF(L56="","Cancelled",IF(L56-K56<=2,"Fast","Slow")) -> Slow | Q56: =_xlfn.XLOOKUP(Orders!B56,'Customer Master'!$A$1:$A$50,'Customer Master'!$B$1:$B$50) -> Emily Johnson | R56: =_xlfn.XLOOKUP(Orders!C56,'Product Master'!$A$1:$A$23,'Product Master'!$C$1:$C$23) -> Home | S56: =_xlfn.XLOOKUP(C56,'Product Master'!$A$1:$A$23,'Product Master'!$B$1:$B$23) -> Wall Clock | T56: =IF(I56="Delivered",G56,0) -> 144
A57: ORD0056 | B57: CUST017 | C57: PROD004 | D57: West | E57: 65 | F57: 1 | G57: 65 | H57: Amazon Pay | I57: Delivered | J57: FedEx | K57: 45217 | L57: 45220 | N57: =IF(M57<>"","Cancelled","Delivered") -> Delivered | O57: =IF(L57<>"",L57-K57,"NA") -> 3 | P57: =IF(L57="","Cancelled",IF(L57-K57<=2,"Fast","Slow")) -> Slow | Q57: =_xlfn.XLOOKUP(Orders!B57,'Customer Master'!$A$1:$A$50,'Customer Master'!$B$1:$B$50) -> Emma King | R57: =_xlfn.XLOOKUP(Orders!C57,'Product Master'!$A$1:$A$23,'Product Master'!$C$1:$C$23) -> Toys | S57: =_xlfn.XLOOKUP(C57,'Product Master'!$A$1:$A$23,'Product Master'!$B$1:$B$23) -> Leg Set | T57: =IF(I57="Delivered",G57,0) -> 65
A58: ORD0057 | B58: CUST025 | C58: PROD005 | D58: Central | E58: 26 | F58: 1 | G58: 26 | H58: Apple Pay | I58: Delivered | J58: DHL | K58: 44933 | L58: 44935 | N58: =IF(M58<>"","Cancelled","Delivered") -> Delivered | O58: =IF(L58<>"",L58-K58,"NA") -> 2 | P58: =IF(L58="","Cancelled",IF(L58-K58<=2,"Fast","Slow")) -> Fast | Q58: =_xlfn.XLOOKUP(Orders!B58,'Customer Master'!$A$1:$A$50,'Customer Master'!$B$1:$B$50) -> Emma King | R58: =_xlfn.XLOOKUP(Orders!C58,'Product Master'!$A$1:$A$23,'Product Master'!$C$1:$C$23) -> Fashion | S58: =_xlfn.XLOOKUP(C58,'Product Master'!$A$1:$A$23,'Product Master'!$B$1:$B$23) -> T-Shirt | T58: =IF(I58="Delivered",G58,0) -> 26
A59: ORD0058 | B59: CUST021 | C59: PROD009 | D59: North | E59: 11 | F59: 5 | G59: 55 | H59: Credit Card | I59: In Transit | J59: FedEx | K59: 45054 | N59: =IF(M59<>"","Cancelled","Delivered") -> Delivered | O59: =IF(L59<>"",L59-K59,"NA") -> NA | P59: =IF(L59="","Cancelled",IF(L59-K59<=2,"Fast","Slow")) -> Cancelled | Q59: =_xlfn.XLOOKUP(Orders!B59,'Customer Master'!$A$1:$A$50,'Customer Master'!$B$1:$B$50) -> Zoe Mitchell | R59: =_xlfn.XLOOKUP(Orders!C59,'Product Master'!$A$1:$A$23,'Product Master'!$C$1:$C$23) -> Books | S59: =_xlfn.XLOOKUP(C59,'Product Master'!$A$1:$A$23,'Product Master'!$B$1:$B$23) -> Magazine | T59: =IF(I59="Delivered",G59,0) -> 0
A60: ORD0059 | B60: CUST003 | C60: PROD013 | D60: North | E60: 195 | F60: 4 | G60: 780 | H60: PayPal | I60: Cancelled | J60: FedEx | K60: 45018 | M60: 45021 | N60: =IF(M60<>"","Cancelled","Delivered") -> Cancelled | O60: =IF(L60<>"",L60-K60,"NA") -> NA | P60: =IF(L60="","Cancelled",IF(L60-K60<=2,"Fast","Slow")) -> Cancelled | Q60: =_xlfn.XLOOKUP(Orders!B60,'Customer Master'!$A$1:$A$50,'Customer Master'!$B$1:$B$50) -> Ethan Davis | R60: =_xlfn.XLOOKUP(Orders!C60,'Product Master'!$A$1:$A$23,'Product Master'!$C$1:$C$23) -> Home | S60: =_xlfn.XLOOKUP(C60,'Product Master'!$A$1:$A$23,'Product Master'!$B$1:$B$23) -> Vacuum Cleaner | T60: =IF(I60="Delivered",G60,0) -> 0
A61: ORD0060 | B61: CUST019 | C61: PROD019 | D61: West | E61: 44 | F61: 5 | G61: 220 | H61: Apple Pay | I61: Cancelled | J61: USPS | K61: 45210 | M61: 45211 | N61: =IF(M61<>"","Cancelled","Delivered") -> Cancelled | O61: =IF(L61<>"",L61-K61,"NA") -> NA | P61: =IF(L61="","Cancelled",IF(L61-K61<=2,"Fast","Slow")) -> Cancelled | Q61: =_xlfn.XLOOKUP(Orders!B61,'Customer Master'!$A$1:$A$50,'Customer Master'!$B$1:$B$50) -> Ava Robinson | R61: =_xlfn.XLOOKUP(Orders!C61,'Product Master'!$A$1:$A$23,'Product Master'!$C$1:$C$23) -> Fashion | S61: =_xlfn.XLOOKUP(C61,'Product Master'!$A$1:$A$23,'Product Master'!$B$1:$B$23) -> Formal Shirt | T61: =IF(I61="Delivered",G61,0) -> 0
A62: ORD0061 | B62: CUST035 | C62: PROD008 | D62: East | E62: 69 | F62: 4 | G62: 276 | H62: Debit Card | I62: In Transit | J62: DHL | K62: 45179 | N62: =IF(M62<>"","Cancelled","Delivered") -> Delivered | O62: =IF(L62<>"",L62-K62,"NA") -> NA | P62: =IF(L62="","Cancelled",IF(L62-K62<=2,"Fast","Slow")) -> Cancelled | Q62: =_xlfn.XLOOKUP(Orders!B62,'Customer Master'!$A$1:$A$50,'Customer Master'!$B$1:$B$50) -> Scarlett Adams | R62: =_xlfn.XLOOKUP(Orders!C62,'Product Master'!$A$1:$A$23,'Product Master'!$C$1:$C$23) -> Books | S62: =_xlfn.XLOOKUP(C62,'Product Master'!$A$1:$A$23,'Product Master'!$B$1:$B$23) -> Textbook | T62: =IF(I62="Delivered",G62,0) -> 0
A63: ORD0062 | B63: CUST022 | C63: PROD001 | D63: North | E63: 815 | F63: 4 | G63: 3260 | H63: Credit Card | I63: Delivered | J63: USPS | K63: 45252 | L63: 45259 | N63: =IF(M63<>"","Cancelled","Delivered") -> Delivered | O63: =IF(L63<>"",L63-K63,"NA") -> 7 | P63: =IF(L63="","Cancelled",IF(L63-K63<=2,"Fast","Slow")) -> Slow | Q63: =_xlfn.XLOOKUP(Orders!B63,'Customer Master'!$A$1:$A$50,'Customer Master'!$B$1:$B$50) -> Elijah Lewis | R63: =_xlfn.XLOOKUP(Orders!C63,'Product Master'!$A$1:$A$23,'Product Master'!$C$1:$C$23) -> Electronics | S63: =_xlfn.XLOOKUP(C63,'Product Master'!$A$1:$A$23,'Product Master'!$B$1:$B$23) -> Smartphone | T63: =IF(I63="Delivered",G63,0) -> 3260
A64: ORD0063 | B64: CUST004 | C64: PROD005 | D64: East | E64: 27 | F64: 1 | G64: 27 | H64: Debit Card | I64: In Transit | J64: Amazon Logistics | K64: 45048 | N64: =IF(M64<>"","Cancelled","Delivered") -> Delivered | O64: =IF(L64<>"",L64-K64,"NA") -> NA | P64: =IF(L64="","Cancelled",IF(L64-K64<=2,"Fast","Slow")) -> Cancelled | Q64: =_xlfn.XLOOKUP(Orders!B64,'Customer Master'!$A$1:$A$50,'Customer Master'!$B$1:$B$50) -> Noah Wilson | R64: =_xlfn.XLOOKUP(Orders!C64,'Product Master'!$A$1:$A$23,'Product Master'!$C$1:$C$23) -> Fashion | S64: =_xlfn.XLOOKUP(C64,'Product Master'!$A$1:$A$23,'Product Master'!$B$1:$B$23) -> T-Shirt | T64: =IF(I64="Delivered",G64,0) -> 0
A65: ORD0064 | B65: CUST048 | C65: PROD003 | D65: West | E65: 139 | F65: 5 | G65: 695 | H65: Apple Pay | I65: Delivered | J65: USPS | K65: 45285 | L65: 45289 | N65: =IF(M65<>"","Cancelled","Delivered") -> Delivered | O65: =IF(L65<>"",L65-K65,"NA") -> 4 | P65: =IF(L65="","Cancelled",IF(L65-K65<=2,"Fast","Slow")) -> Slow | Q65: =_xlfn.XLOOKUP(Orders!B65,'Customer Master'!$A$1:$A$50,'Customer Master'!$B$1:$B$50) -> Noah Wilson | R65: =_xlfn.XLOOKUP(Orders!C65,'Product Master'!$A$1:$A$23,'Product Master'!$C$1:$C$23) -> Home | S65: =_xlfn.XLOOKUP(C65,'Product Master'!$A$1:$A$23,'Product Master'!$B$1:$B$23) -> Cookware Set | T65: =IF(I65="Delivered",G65,0) -> 695
A66: ORD0065 | B66: CUST009 | C66: PROD008 | D66: South | E66: 69 | F66: 3 | G66: 207 | H66: PayPal | I66: Cancelled | J66: Amazon Logistics | K66: 45217 | M66: 45219 | N66: =IF(M66<>"","Cancelled","Delivered") -> Cancelled | O66: =IF(L66<>"",L66-K66,"NA") -> NA | P66: =IF(L66="","Cancelled",IF(L66-K66<=2,"Fast","Slow")) -> Cancelled | Q66: =_xlfn.XLOOKUP(Orders!B66,'Customer Master'!$A$1:$A$50,'Customer Master'!$B$1:$B$50) -> Jackson Allen | R66: =_xlfn.XLOOKUP(Orders!C66,'Product Master'!$A$1:$A$23,'Product Master'!$C$1:$C$23) -> Books | S66: =_xlfn.XLOOKUP(C66,'Product Master'!$A$1:$A$23,'Product Master'!$B$1:$B$23) -> Textbook | T66: =IF(I66="Delivered",G66,0) -> 0
A67: ORD0066 | B67: CUST009 | C67: PROD019 | D67: West | E67: 42 | F67: 1 | G67: 42 | H67: Apple Pay | I67: Cancelled | J67: DHL | K67: 45066 | M67: 45067 | N67: =IF(M67<>"","Cancelled","Delivered") -> Cancelled | O67: =IF(L67<>"",L67-K67,"NA") -> NA | P67: =IF(L67="","Cancelled",IF(L67-K67<=2,"Fast","Slow")) -> Cancelled | Q67: =_xlfn.XLOOKUP(Orders!B67,'Customer Master'!$A$1:$A$50,'Customer Master'!$B$1:$B$50) -> Jackson Allen | R67: =_xlfn.XLOOKUP(Orders!C67,'Product Master'!$A$1:$A$23,'Product Master'!$C$1:$C$23) -> Fashion | S67: =_xlfn.XLOOKUP(C67,'Product Master'!$A$1:$A$23,'Product Master'!$B$1:$B$23) -> Formal Shirt | T67: =IF(I67="Delivered",G67,0) -> 0
A68: ORD0067 | B68: CUST050 | C68: PROD007 | D68: North | E68: 31 | F68: 4 | G68: 124 | H68: Credit Card | I68: Delivered | J68: UPS | K68: 45135 | L68: 45137 | N68: =IF(M68<>"","Cancelled","Delivered") -> Delivered | O68: =IF(L68<>"",L68-K68,"NA") -> 2 | P68: =IF(L68="","Cancelled",IF(L68-K68<=2,"Fast","Slow")) -> Fast | Q68: =_xlfn.XLOOKUP(Orders!B68,'Customer Master'!$A$1:$A$50,'Customer Master'!$B$1:$B$50) -> #N/A | R68: =_xlfn.XLOOKUP(Orders!C68,'Product Master'!$A$1:$A$23,'Product Master'!$C$1:$C$23) -> Toys | S68: =_xlfn.XLOOKUP(C68,'Product Master'!$A$1:$A$23,'Product Master'!$B$1:$B$23) -> Puzzle | T68: =IF(I68="Delivered",G68,0) -> 124
A69: ORD0068 | B69: CUST045 | C69: PROD020 | D69: West | E69: 104 | F69: 3 | G69: 312 | H69: Credit Card | I69: In Transit | J69: UPS | K69: 45278 | N69: =IF(M69<>"","Cancelled","Delivered") -> Delivered | O69: =IF(L69<>"",L69-K69,"NA") -> NA | P69: =IF(L69="","Cancelled",IF(L69-K69<=2,"Fast","Slow")) -> Cancelled | Q69: =_xlfn.XLOOKUP(Orders!B69,'Customer Master'!$A$1:$A$50,'Customer Master'!$B$1:$B$50) -> Emily Johnson | R69: =_xlfn.XLOOKUP(Orders!C69,'Product Master'!$A$1:$A$23,'Product Master'!$C$1:$C$23) -> Electronics | S69: =_xlfn.XLOOKUP(C69,'Product Master'!$A$1:$A$23,'Product Master'!$B$1:$B$23) -> Bluetooth Speaker | T69: =IF(I69="Delivered",G69,0) -> 0
A70: ORD0069 | B70: CUST044 | C70: PROD010 | D70: East | E70: 58 | F70: 2 | G70: 116 | H70: Apple Pay | I70: Cancelled | J70: USPS | K70: 45109 | M70: 45114 | N70: =IF(M70<>"","Cancelled","Delivered") -> Cancelled | O70: =IF(L70<>"",L70-K70,"NA") -> NA | P70: =IF(L70="","Cancelled",IF(L70-K70<=2,"Fast","Slow")) -> Cancelled | Q70: =_xlfn.XLOOKUP(Orders!B70,'Customer Master'!$A$1:$A$50,'Customer Master'!$B$1:$B$50) -> Grace Ward | R70: =_xlfn.XLOOKUP(Orders!C70,'Product Master'!$A$1:$A$23,'Product Master'!$C$1:$C$23) -> Fashion | S70: =_xlfn.XLOOKUP(C70,'Product Master'!$A$1:$A$23,'Product Master'!$B$1:$B$23) -> Jeans | T70: =IF(I70="Delivered",G70,0) -> 0
A71: ORD0070 | B71: CUST009 | C71: PROD004 | D71: West | E71: 62 | F71: 2 | G71: 124 | H71: Debit Card | I71: Cancelled | J71: DHL | K71: 45208 | M71: 45209 | N71: =IF(M71<>"","Cancelled","Delivered") -> Cancelled | O71: =IF(L71<>"",L71-K71,"NA") -> NA | P71: =IF(L71="","Cancelled",IF(L71-K71<=2,"Fast","Slow")) -> Cancelled | Q71: =_xlfn.XLOOKUP(Orders!B71,'Customer Master'!$A$1:$A$50,'Customer Master'!$B$1:$B$50) -> Jackson Allen | R71: =_xlfn.XLOOKUP(Orders!C71,'Product Master'!$A$1:$A$23,'Product Master'!$C$1:$C$23) -> Toys | S71: =_xlfn.XLOOKUP(C71,'Product Master'!$A$1:$A$23,'Product Master'!$B$1:$B$23) -> Leg Set | T71: =IF(I71="Delivered",G71,0) -> 0
A72: ORD0071 | B72: CUST006 | C72: PROD019 | D72: East | E72: 43 | F72: 1 | G72: 43 | H72: Credit Card | I72: Delivered | J72: Amazon Logistics | K72: 45278 | L72: 45285 | N72: =IF(M72<>"","Cancelled","Delivered") -> Delivered | O72: =IF(L72<>"",L72-K72,"NA") -> 7 | P72: =IF(L72="","Cancelled",IF(L72-K72<=2,"Fast","Slow")) -> Slow | Q72: =_xlfn.XLOOKUP(Orders!B72,'Customer Master'!$A$1:$A$50,'Customer Master'!$B$1:$B$50) -> Ava Robinson | R72: =_xlfn.XLOOKUP(Orders!C72,'Product Master'!$A$1:$A$23,'Product Master'!$C$1:$C$23) -> Fashion | S72: =_xlfn.XLOOKUP(C72,'Product Master'!$A$1:$A$23,'Product Master'!$B$1:$B$23) -> Formal Shirt | T72: =IF(I72="Delivered",G72,0) -> 43
A73: ORD0072 | B73: CUST022 | C73: PROD004 | D73: East | E73: 62 | F73: 4 | G73: 248 | H73: Debit Card | I73: In Transit | J73: Amazon Logistics | K73: 44992 | N73: =IF(M73<>"","Cancelled","Delivered") -> Delivered | O73: =IF(L73<>"",L73-K73,"NA") -> NA | P73: =IF(L73="","Cancelled",IF(L73-K73<=2,"Fast","Slow")) -> Cancelled | Q73: =_xlfn.XLOOKUP(Orders!B73,'Customer Master'!$A$1:$A$50,'Customer Master'!$B$1:$B$50) -> Elijah Lewis | R73: =_xlfn.XLOOKUP(Orders!C73,'Product Master'!$A$1:$A$23,'Product Master'!$C$1:$C$23) -> Toys | S73: =_xlfn.XLOOKUP(C73,'Product Master'!$A$1:$A$23,'Product Master'!$B$1:$B$23) -> Leg Set | T73: =IF(I73="Delivered",G73,0) -> 0
A74: ORD0073 | B74: CUST028 | C74: PROD006 | D74: North | E74: 95 | F74: 2 | G74: 190 | H74: PayPal | I74: Cancelled | J74: UPS | K74: 45129 | M74: 45132 | N74: =IF(M74<>"","Cancelled","Delivered") -> Cancelled | O74: =IF(L74<>"",L74-K74,"NA") -> NA | P74: =IF(L74="","Cancelled",IF(L74-K74<=2,"Fast","Slow")) -> Cancelled | Q74: =_xlfn.XLOOKUP(Orders!B74,'Customer Master'!$A$1:$A$50,'Customer Master'!$B$1:$B$50) -> Lily Bennett | R74: =_xlfn.XLOOKUP(Orders!C74,'Product Master'!$A$1:$A$23,'Product Master'!$C$1:$C$23) -> Fashion | S74: =_xlfn.XLOOKUP(C74,'Product Master'!$A$1:$A$23,'Product Master'!$B$1:$B$23) -> Shoes | T74: =IF(I74="Delivered",G74,0) -> 0
A75: ORD0074 | B75: CUST016 | C75: PROD021 | D75: Central | E75: 36 | F75: 4 | G75: 144 | H75: Apple Pay | I75: Delivered | J75: FedEx | K75: 44944 | L75: 44950 | N75: =IF(M75<>"","Cancelled","Delivered") -> Delivered | O75: =IF(L75<>"",L75-K75,"NA") -> 6 | P75: =IF(L75="","Cancelled",IF(L75-K75<=2,"Fast","Slow")) -> Slow | Q75: =_xlfn.XLOOKUP(Orders!B75,'Customer Master'!$A$1:$A$50,'Customer Master'!$B$1:$B$50) -> Elijah Lewis | R75: =_xlfn.XLOOKUP(Orders!C75,'Product Master'!$A$1:$A$23,'Product Master'!$C$1:$C$23) -> Home | S75: =_xlfn.XLOOKUP(C75,'Product Master'!$A$1:$A$23,'Product Master'!$B$1:$B$23) -> Wall Clock | T75: =IF(I75="Delivered",G75,0) -> 144
A76: ORD0075 | B76: CUST042 | C76: PROD017 | D76: East | E76: 73 | F76: 5 | G76: 365 | H76: Apple Pay | I76: In Transit | J76: DHL | K76: 45070 | N76: =IF(M76<>"","Cancelled","Delivered") -> Delivered | O76: =IF(L76<>"",L76-K76,"NA") -> NA | P76: =IF(L76="","Cancelled",IF(L76-K76<=2,"Fast","Slow")) -> Cancelled | Q76: =_xlfn.XLOOKUP(Orders!B76,'Customer Master'!$A$1:$A$50,'Customer Master'!$B$1:$B$50) -> Noah Wilson | R76: =_xlfn.XLOOKUP(Orders!C76,'Product Master'!$A$1:$A$23,'Product Master'!$C$1:$C$23) -> Electronics | S76: =_xlfn.XLOOKUP(C76,'Product Master'!$A$1:$A$23,'Product Master'!$B$1:$B$23) -> Gaming Mouse | T76: =IF(I76="Delivered",G76,0) -> 0
A77: ORD0076 | B77: CUST023 | C77: PROD019 | D77: North | E77: 43 | F77: 4 | G77: 172 | H77: Debit Card | I77: Delivered | J77: DHL | K77: 45172 | L77: 45178 | N77: =IF(M77<>"","Cancelled","Delivered") -> Delivered | O77: =IF(L77<>"",L77-K77,"NA") -> 6 | P77: =IF(L77="","Cancelled",IF(L77-K77<=2,"Fast","Slow")) -> Slow | Q77: =_xlfn.XLOOKUP(Orders!B77,'Customer Master'!$A$1:$A$50,'Customer Master'!$B$1:$B$50) -> Charlotte Reed | R77: =_xlfn.XLOOKUP(Orders!C77,'Product Master'!$A$1:$A$23,'Product Master'!$C$1:$C$23) -> Fashion | S77: =_xlfn.XLOOKUP(C77,'Product Master'!$A$1:$A$23,'Product Master'!$B$1:$B$23) -> Formal Shirt | T77: =IF(I77="Delivered",G77,0) -> 172
A78: ORD0077 | B78: CUST004 | C78: PROD016 | D78: West | E78: 214 | F78: 5 | G78: 1070 | H78: Debit Card | I78: Delivered | J78: UPS | K78: 45232 | L78: 45234 | N78: =IF(M78<>"","Cancelled","Delivered") -> Delivered | O78: =IF(L78<>"",L78-K78,"NA") -> 2 | P78: =IF(L78="","Cancelled",IF(L78-K78<=2,"Fast","Slow")) -> Fast | Q78: =_xlfn.XLOOKUP(Orders!B78,'Customer Master'!$A$1:$A$50,'Customer Master'!$B$1:$B$50) -> Noah Wilson | R78: =_xlfn.XLOOKUP(Orders!C78,'Product Master'!$A$1:$A$23,'Product Master'!$C$1:$C$23) -> Home | S78: =_xlfn.XLOOKUP(C78,'Product Master'!$A$1:$A$23,'Product Master'!$B$1:$B$23) -> Cookware Set Pro | T78: =IF(I78="Delivered",G78,0) -> 1070
A79: ORD0078 | B79: CUST048 | C79: PROD002 | D79: Central | E79: 42 | F79: 2 | G79: 84 | H79: Apple Pay | I79: Cancelled | J79: UPS | K79: 45263 | M79: 45266 | N79: =IF(M79<>"","Cancelled","Delivered") -> Cancelled | O79: =IF(L79<>"",L79-K79,"NA") -> NA | P79: =IF(L79="","Cancelled",IF(L79-K79<=2,"Fast","Slow")) -> Cancelled | Q79: =_xlfn.XLOOKUP(Orders!B79,'Customer Master'!$A$1:$A$50,'Customer Master'!$B$1:$B$50) -> Noah Wilson | R79: =_xlfn.XLOOKUP(Orders!C79,'Product Master'!$A$1:$A$23,'Product Master'!$C$1:$C$23) -> Toys | S79: =_xlfn.XLOOKUP(C79,'Product Master'!$A$1:$A$23,'Product Master'!$B$1:$B$23) -> Action Figure | T79: =IF(I79="Delivered",G79,0) -> 0
A80: ORD0079 | B80: CUST048 | C80: PROD012 | D80: North | E80: 46 | F80: 1 | G80: 46 | H80: Amazon Pay | I80: In Transit | J80: UPS | K80: 45017 | N80: =IF(M80<>"","Cancelled","Delivered") -> Delivered | O80: =IF(L80<>"",L80-K80,"NA") -> NA | P80: =IF(L80="","Cancelled",IF(L80-K80<=2,"Fast","Slow")) -> Cancelled | Q80: =_xlfn.XLOOKUP(Orders!B80,'Customer Master'!$A$1:$A$50,'Customer Master'!$B$1:$B$50) -> Noah Wilson | R80: =_xlfn.XLOOKUP(Orders!C80,'Product Master'!$A$1:$A$23,'Product Master'!$C$1:$C$23) -> Home | S80: =_xlfn.XLOOKUP(C80,'Product Master'!$A$1:$A$23,'Product Master'!$B$1:$B$23) -> Lamp | T80: =IF(I80="Delivered",G80,0) -> 0
A81: ORD0080 | B81: CUST032 | C81: PROD018 | D81: East | E81: 95 | F81: 4 | G81: 380 | H81: Credit Card | I81: Delivered | J81: UPS | K81: 45215 | L81: 45218 | N81: =IF(M81<>"","Cancelled","Delivered") -> Delivered | O81: =IF(L81<>"",L81-K81,"NA") -> 3 | P81: =IF(L81="","Cancelled",IF(L81-K81<=2,"Fast","Slow")) -> Slow | Q81: =_xlfn.XLOOKUP(Orders!B81,'Customer Master'!$A$1:$A$50,'Customer Master'!$B$1:$B$50) -> Luke Gray | R81: =_xlfn.XLOOKUP(Orders!C81,'Product Master'!$A$1:$A$23,'Product Master'!$C$1:$C$23) -> Toys | S81: =_xlfn.XLOOKUP(C81,'Product Master'!$A$1:$A$23,'Product Master'!$B$1:$B$23) -> Doll House | T81: =IF(I81="Delivered",G81,0) -> 380
A82: ORD0081 | B82: CUST001 | C82: PROD011 | D82: West | E82: 174 | F82: 2 | G82: 348 | H82: PayPal | I82: In Transit | J82: UPS | K82: 45235 | N82: =IF(M82<>"","Cancelled","Delivered") -> Delivered | O82: =IF(L82<>"",L82-K82,"NA") -> NA | P82: =IF(L82="","Cancelled",IF(L82-K82<=2,"Fast","Slow")) -> Cancelled | Q82: =_xlfn.XLOOKUP(Orders!B82,'Customer Master'!$A$1:$A$50,'Customer Master'!$B$1:$B$50) -> James Miller | R82: =_xlfn.XLOOKUP(Orders!C82,'Product Master'!$A$1:$A$23,'Product Master'!$C$1:$C$23) -> Electronics | S82: =_xlfn.XLOOKUP(C82,'Product Master'!$A$1:$A$23,'Product Master'!$B$1:$B$23) -> Headphones | T82: =IF(I82="Delivered",G82,0) -> 0
A83: ORD0082 | B83: CUST046 | C83: PROD005 | D83: North | E83: 27 | F83: 5 | G83: 135 | H83: Credit Card | I83: Cancelled | J83: Amazon Logistics | K83: 45092 | M83: 45095 | N83: =IF(M83<>"","Cancelled","Delivered") -> Cancelled | O83: =IF(L83<>"",L83-K83,"NA") -> NA | P83: =IF(L83="","Cancelled",IF(L83-K83<=2,"Fast","Slow")) -> Cancelled | Q83: =_xlfn.XLOOKUP(Orders!B83,'Customer Master'!$A$1:$A$50,'Customer Master'!$B$1:$B$50) -> Emily Johnson | R83: =_xlfn.XLOOKUP(Orders!C83,'Product Master'!$A$1:$A$23,'Product Master'!$C$1:$C$23) -> Fashion | S83: =_xlfn.XLOOKUP(C83,'Product Master'!$A$1:$A$23,'Product Master'!$B$1:$B$23) -> T-Shirt | T83: =IF(I83="Delivered",G83,0) -> 0
A84: ORD0083 | B84: CUST021 | C84: PROD005 | D84: South | E84: 27 | F84: 4 | G84: 108 | H84: PayPal | I84: Delivered | J84: USPS | K84: 45227 | L84: 45229 | N84: =IF(M84<>"","Cancelled","Delivered") -> Delivered | O84: =IF(L84<>"",L84-K84,"NA") -> 2 | P84: =IF(L84="","Cancelled",IF(L84-K84<=2,"Fast","Slow")) -> Fast | Q84: =_xlfn.XLOOKUP(Orders!B84,'Customer Master'!$A$1:$A$50,'Customer Master'!$B$1:$B$50) -> Zoe Mitchell | R84: =_xlfn.XLOOKUP(Orders!C84,'Product Master'!$A$1:$A$23,'Product Master'!$C$1:$C$23) -> Fashion | S84: =_xlfn.XLOOKUP(C84,'Product Master'!$A$1:$A$23,'Product Master'!$B$1:$B$23) -> T-Shirt | T84: =IF(I84="Delivered",G84,0) -> 108
A85: ORD0084 | B85: CUST015 | C85: PROD022 | D85: South | E85: 65 | F85: 2 | G85: 130 | H85: PayPal | I85: In Transit | J85: DHL | K85: 45282 | N85: =IF(M85<>"","Cancelled","Delivered") -> Delivered | O85: =IF(L85<>"",L85-K85,"NA") -> NA | P85: =IF(L85="","Cancelled",IF(L85-K85<=2,"Fast","Slow")) -> Cancelled | Q85: =_xlfn.XLOOKUP(Orders!B85,'Customer Master'!$A$1:$A$50,'Customer Master'!$B$1:$B$50) -> Ava White | R85: =_xlfn.XLOOKUP(Orders!C85,'Product Master'!$A$1:$A$23,'Product Master'!$C$1:$C$23) -> Fashion | S85: =_xlfn.XLOOKUP(C85,'Product Master'!$A$1:$A$23,'Product Master'!$B$1:$B$23) -> Backpack | T85: =IF(I85="Delivered",G85,0) -> 0
A86: ORD0085 | B86: CUST045 | C86: PROD019 | D86: East | E86: 43 | F86: 5 | G86: 215 | H86: Debit Card | I86: In Transit | J86: DHL | K86: 44992 | N86: =IF(M86<>"","Cancelled","Delivered") -> Delivered | O86: =IF(L86<>"",L86-K86,"NA") -> NA | P86: =IF(L86="","Cancelled",IF(L86-K86<=2,"Fast","Slow")) -> Cancelled | Q86: =_xlfn.XLOOKUP(Orders!B86,'Customer Master'!$A$1:$A$50,'Customer Master'!$B$1:$B$50) -> Emily Johnson | R86: =_xlfn.XLOOKUP(Orders!C86,'Product Master'!$A$1:$A$23,'Product Master'!$C$1:$C$23) -> Fashion | S86: =_xlfn.XLOOKUP(C86,'Product Master'!$A$1:$A$23,'Product Master'!$B$1:$B$23) -> Formal Shirt | T86: =IF(I86="Delivered",G86,0) -> 0
A87: ORD0086 | B87: CUST007 | C87: PROD016 | D87: West | E87: 210 | F87: 1 | G87: 210 | H87: PayPal | I87: In Transit | J87: UPS | K87: 45240 | N87: =IF(M87<>"","Cancelled","Delivered") -> Delivered | O87: =IF(L87<>"",L87-K87,"NA") -> NA | P87: =IF(L87="","Cancelled",IF(L87-K87<=2,"Fast","Slow")) -> Cancelled | Q87: =_xlfn.XLOOKUP(Orders!B87,'Customer Master'!$A$1:$A$50,'Customer Master'!$B$1:$B$50) -> Liam Walker | R87: =_xlfn.XLOOKUP(Orders!C87,'Product Master'!$A$1:$A$23,'Product Master'!$C$1:$C$23) -> Home | S87: =_xlfn.XLOOKUP(C87,'Product Master'!$A$1:$A$23,'Product Master'!$B$1:$B$23) -> Cookware Set Pro | T87: =IF(I87="Delivered",G87,0) -> 0
A88: ORD0087 | B88: CUST043 | C88: PROD021 | D88: South | E88: 37 | F88: 3 | G88: 111 | H88: Credit Card | I88: In Transit | J88: UPS | K88: 45252 | N88: =IF(M88<>"","Cancelled","Delivered") -> Delivered | O88: =IF(L88<>"",L88-K88,"NA") -> NA | P88: =IF(L88="","Cancelled",IF(L88-K88<=2,"Fast","Slow")) -> Cancelled | Q88: =_xlfn.XLOOKUP(Orders!B88,'Customer Master'!$A$1:$A$50,'Customer Master'!$B$1:$B$50) -> Lily Reed | R88: =_xlfn.XLOOKUP(Orders!C88,'Product Master'!$A$1:$A$23,'Product Master'!$C$1:$C$23) -> Home | S88: =_xlfn.XLOOKUP(C88,'Product Master'!$A$1:$A$23,'Product Master'!$B$1:$B$23) -> Wall Clock | T88: =IF(I88="Delivered",G88,0) -> 0
A89: ORD0088 | B89: CUST007 | C89: PROD001 | D89: South | E89: 788 | F89: 4 | G89: 3152 | H89: Debit Card | I89: In Transit | J89: Amazon Logistics | K89: 45054 | N89: =IF(M89<>"","Cancelled","Delivered") -> Delivered | O89: =IF(L89<>"",L89-K89,"NA") -> NA | P89: =IF(L89="","Cancelled",IF(L89-K89<=2,"Fast","Slow")) -> Cancelled | Q89: =_xlfn.XLOOKUP(Orders!B89,'Customer Master'!$A$1:$A$50,'Customer Master'!$B$1:$B$50) -> Liam Walker | R89: =_xlfn.XLOOKUP(Orders!C89,'Product Master'!$A$1:$A$23,'Product Master'!$C$1:$C$23) -> Electronics | S89: =_xlfn.XLOOKUP(C89,'Product Master'!$A$1:$A$23,'Product Master'!$B$1:$B$23) -> Smartphone | T89: =IF(I89="Delivered",G89,0) -> 0
A90: ORD0089 | B90: CUST007 | C90: PROD016 | D90: West | E90: 217 | F90: 5 | G90: 1085 | H90: Debit Card | I90: In Transit | J90: FedEx | K90: 45120 | N90: =IF(M90<>"","Cancelled","Delivered") -> Delivered | O90: =IF(L90<>"",L90-K90,"NA") -> NA | P90: =IF(L90="","Cancelled",IF(L90-K90<=2,"Fast","Slow")) -> Cancelled | Q90: =_xlfn.XLOOKUP(Orders!B90,'Customer Master'!$A$1:$A$50,'Customer Master'!$B$1:$B$50) -> Liam Walker | R90: =_xlfn.XLOOKUP(Orders!C90,'Product Master'!$A$1:$A$23,'Product Master'!$C$1:$C$23) -> Home | S90: =_xlfn.XLOOKUP(C90,'Product Master'!$A$1:$A$23,'Product Master'!$B$1:$B$23) -> Cookware Set Pro | T90: =IF(I90="Delivered",G90,0) -> 0
A91: ORD0090 | B91: CUST007 | C91: PROD003 | D91: West | E91: 138 | F91: 4 | G91: 552 | H91: Credit Card | I91: In Transit | J91: FedEx | K91: 44944 | N91: =IF(M91<>"","Cancelled","Delivered") -> Delivered | O91: =IF(L91<>"",L91-K91,"NA") -> NA | P91: =IF(L91="","Cancelled",IF(L91-K91<=2,"Fast","Slow")) -> Cancelled | Q91: =_xlfn.XLOOKUP(Orders!B91,'Customer Master'!$A$1:$A$50,'Customer Master'!$B$1:$B$50) -> Liam Walker | R91: =_xlfn.XLOOKUP(Orders!C91,'Product Master'!$A$1:$A$23,'Product Master'!$C$1:$C$23) -> Home | S91: =_xlfn.XLOOKUP(C91,'Product Master'!$A$1:$A$23,'Product Master'!$B$1:$B$23) -> Cookware Set | T91: =IF(I91="Delivered",G91,0) -> 0
A92: ORD0091 | B92: CUST031 | C92: PROD001 | D92: Central | E92: 803 | F92: 2 | G92: 1606 | H92: Apple Pay | I92: Delivered | J92: FedEx | K92: 45100 | L92: 45106 | N92: =IF(M92<>"","Cancelled","Delivered") -> Delivered | O92: =IF(L92<>"",L92-K92,"NA") -> 6 | P92: =IF(L92="","Cancelled",IF(L92-K92<=2,"Fast","Slow")) -> Slow | Q92: =_xlfn.XLOOKUP(Orders!B92,'Customer Master'!$A$1:$A$50,'Customer Master'!$B$1:$B$50) -> Mason Collins | R92: =_xlfn.XLOOKUP(Orders!C92,'Product Master'!$A$1:$A$23,'Product Master'!$C$1:$C$23) -> Electronics | S92: =_xlfn.XLOOKUP(C92,'Product Master'!$A$1:$A$23,'Product Master'!$B$1:$B$23) -> Smartphone | T92: =IF(I92="Delivered",G92,0) -> 1606
A93: ORD0092 | B93: CUST013 | C93: PROD014 | D93: North | E93: 248 | F93: 5 | G93: 1240 | H93: PayPal | I93: Cancelled | J93: UPS | K93: 44978 | M93: 44982 | N93: =IF(M93<>"","Cancelled","Delivered") -> Cancelled | O93: =IF(L93<>"",L93-K93,"NA") -> NA | P93: =IF(L93="","Cancelled",IF(L93-K93<=2,"Fast","Slow")) -> Cancelled | Q93: =_xlfn.XLOOKUP(Orders!B93,'Customer Master'!$A$1:$A$50,'Customer Master'!$B$1:$B$50) -> Olivia Martinez | R93: =_xlfn.XLOOKUP(Orders!C93,'Product Master'!$A$1:$A$23,'Product Master'!$C$1:$C$23) -> Electronics | S93: =_xlfn.XLOOKUP(C93,'Product Master'!$A$1:$A$23,'Product Master'!$B$1:$B$23) -> Smartwatch | T93: =IF(I93="Delivered",G93,0) -> 0
A94: ORD0093 | B94: CUST036 | C94: PROD016 | D94: East | E94: 210 | F94: 3 | G94: 630 | H94: Apple Pay | I94: Delivered | J94: DHL | K94: 44976 | L94: 44978 | N94: =IF(M94<>"","Cancelled","Delivered") -> Delivered | O94: =IF(L94<>"",L94-K94,"NA") -> 2 | P94: =IF(L94="","Cancelled",IF(L94-K94<=2,"Fast","Slow")) -> Fast | Q94: =_xlfn.XLOOKUP(Orders!B94,'Customer Master'!$A$1:$A$50,'Customer Master'!$B$1:$B$50) -> Ethan Davis | R94: =_xlfn.XLOOKUP(Orders!C94,'Product Master'!$A$1:$A$23,'Product Master'!$C$1:$C$23) -> Home | S94: =_xlfn.XLOOKUP(C94,'Product Master'!$A$1:$A$23,'Product Master'!$B$1:$B$23) -> Cookware Set Pro | T94: =IF(I94="Delivered",G94,0) -> 630
A95: ORD0094 | B95: CUST013 | C95: PROD004 | D95: North | E95: 62 | F95: 2 | G95: 124 | H95: Credit Card | I95: Cancelled | J95: FedEx | K95: 45265 | M95: 45272 | N95: =IF(M95<>"","Cancelled","Delivered") -> Cancelled | O95: =IF(L95<>"",L95-K95,"NA") -> NA | P95: =IF(L95="","Cancelled",IF(L95-K95<=2,"Fast","Slow")) -> Cancelled | Q95: =_xlfn.XLOOKUP(Orders!B95,'Customer Master'!$A$1:$A$50,'Customer Master'!$B$1:$B$50) -> Olivia Martinez | R95: =_xlfn.XLOOKUP(Orders!C95,'Product Master'!$A$1:$A$23,'Product Master'!$C$1:$C$23) -> Toys | S95: =_xlfn.XLOOKUP(C95,'Product Master'!$A$1:$A$23,'Product Master'!$B$1:$B$23) -> Leg Set | T95: =IF(I95="Delivered",G95,0) -> 0
A96: ORD0095 | B96: CUST043 | C96: PROD009 | D96: South | E96: 11 | F96: 5 | G96: 55 | H96: Debit Card | I96: Cancelled | J96: Amazon Logistics | K96: 45084 | M96: 45089 | N96: =IF(M96<>"","Cancelled","Delivered") -> Cancelled | O96: =IF(L96<>"",L96-K96,"NA") -> NA | P96: =IF(L96="","Cancelled",IF(L96-K96<=2,"Fast","Slow")) -> Cancelled | Q96: =_xlfn.XLOOKUP(Orders!B96,'Customer Master'!$A$1:$A$50,'Customer Master'!$B$1:$B$50) -> Lily Reed | R96: =_xlfn.XLOOKUP(Orders!C96,'Product Master'!$A$1:$A$23,'Product Master'!$C$1:$C$23) -> Books | S96: =_xlfn.XLOOKUP(C96,'Product Master'!$A$1:$A$23,'Product Master'!$B$1:$B$23) -> Magazine | T96: =IF(I96="Delivered",G96,0) -> 0
A97: ORD0096 | B97: CUST017 | C97: PROD015 | D97: North | E97: 21 | F97: 2 | G97: 42 | H97: Amazon Pay | I97: Delivered | J97: UPS | K97: 45116 | L97: 45119 | N97: =IF(M97<>"","Cancelled","Delivered") -> Delivered | O97: =IF(L97<>"",L97-K97,"NA") -> 3 | P97: =IF(L97="","Cancelled",IF(L97-K97<=2,"Fast","Slow")) -> Slow | Q97: =_xlfn.XLOOKUP(Orders!B97,'Customer Master'!$A$1:$A$50,'Customer Master'!$B$1:$B$50) -> Emma King | R97: =_xlfn.XLOOKUP(Orders!C97,'Product Master'!$A$1:$A$23,'Product Master'!$C$1:$C$23) -> Books | S97: =_xlfn.XLOOKUP(C97,'Product Master'!$A$1:$A$23,'Product Master'!$B$1:$B$23) -> Novel | T97: =IF(I97="Delivered",G97,0) -> 42
A98: ORD0097 | B98: CUST023 | C98: PROD018 | D98: West | E98: 95 | F98: 5 | G98: 475 | H98: Amazon Pay | I98: Delivered | J98: Amazon Logistics | K98: 45283 | L98: 45286 | N98: =IF(M98<>"","Cancelled","Delivered") -> Delivered | O98: =IF(L98<>"",L98-K98,"NA") -> 3 | P98: =IF(L98="","Cancelled",IF(L98-K98<=2,"Fast","Slow")) -> Slow | Q98: =_xlfn.XLOOKUP(Orders!B98,'Customer Master'!$A$1:$A$50,'Customer Master'!$B$1:$B$50) -> Charlotte Reed | R98: =_xlfn.XLOOKUP(Orders!C98,'Product Master'!$A$1:$A$23,'Product Master'!$C$1:$C$23) -> Toys | S98: =_xlfn.XLOOKUP(C98,'Product Master'!$A$1:$A$23,'Product Master'!$B$1:$B$23) -> Doll House | T98: =IF(I98="Delivered",G98,0) -> 475
A99: ORD0098 | B99: CUST044 | C99: PROD016 | D99: South | E99: 215 | F99: 2 | G99: 430 | H99: PayPal | I99: Delivered | J99: Amazon Logistics | K99: 45194 | L99: 45199 | N99: =IF(M99<>"","Cancelled","Delivered") -> Delivered | O99: =IF(L99<>"",L99-K99,"NA") -> 5 | P99: =IF(L99="","Cancelled",IF(L99-K99<=2,"Fast","Slow")) -> Slow | Q99: =_xlfn.XLOOKUP(Orders!B99,'Customer Master'!$A$1:$A$50,'Customer Master'!$B$1:$B$50) -> Grace Ward | R99: =_xlfn.XLOOKUP(Orders!C99,'Product Master'!$A$1:$A$23,'Product Master'!$C$1:$C$23) -> Home | S99: =_xlfn.XLOOKUP(C99,'Product Master'!$A$1:$A$23,'Product Master'!$B$1:$B$23) -> Cookware Set Pro | T99: =IF(I99="Delivered",G99,0) -> 430
A100: ORD0099 | B100: CUST034 | C100: PROD019 | D100: West | E100: 43 | F100: 5 | G100: 215 | H100: Credit Card | I100: Cancelled | J100: UPS | K100: 44944 | M100: 44950 | N100: =IF(M100<>"","Cancelled","Delivered") -> Cancelled | O100: =IF(L100<>"",L100-K100,"NA") -> NA | P100: =IF(L100="","Cancelled",IF(L100-K100<=2,"Fast","Slow")) -> Cancelled | Q100: =_xlfn.XLOOKUP(Orders!B100,'Customer Master'!$A$1:$A$50,'Customer Master'!$B$1:$B$50) -> Lily Simmons | R100: =_xlfn.XLOOKUP(Orders!C100,'Product Master'!$A$1:$A$23,'Product Master'!$C$1:$C$23) -> Fashion | S100: =_xlfn.XLOOKUP(C100,'Product Master'!$A$1:$A$23,'Product Master'!$B$1:$B$23) -> Formal Shirt | T100: =IF(I100="Delivered",G100,0) -> 0
...

Sheet Product Master
A1: Product ID | B1: Product Name | C1: Category | D1: Cost Price | E1: Description
A2: PROD001 | B2: Smartphone | C2: Electronics | D2: 749 | E2: Latest model with 5G, dual SIM, and OLED display
A3: PROD002 | B3: Action Figure | C3: Toys | D3: 39 | E3: Collectible superhero action figure for ages 8+
A4: PROD003 | B4: Cookware Set | C4: Home | D4: 129 | E4: Non-stick 5-piece cookware set for daily use
A5: PROD004 | B5: Leg Set | C5: Toys | D5: 59 | E5: 300-piece creative building block toy set
A6: PROD005 | B6: T-Shirt | C6: Fashion | D6: 25 | E6: Cotton t-shirt, available in multiple colors
A7: PROD006 | B7: Shoes | C7: Fashion | D7: 89 | E7: Casual wear shoes for men and women
A8: PROD007 | B8: Puzzle | C8: Toys | D8: 29 | E8: 1000-piece jigsaw puzzle
A9: PROD008 | B9: Textbook | C9: Books | D9: 65 | E9: University-level textbook on computer science
A10: PROD009 | B10: Magazine | C10: Books | D10: 10 | E10: Monthly lifestyle magazine
A11: PROD010 | B11: Jeans | C11: Fashion | D11: 55 | E11: Slim fit denim jeans with stretch
A12: PROD011 | B12: Headphones | C12: Electronics | D12: 159 | E12: Wireless noise-cancelling over-ear headphones
A13: PROD012 | B13: Lamp | C13: Home | D13: 42 | E13: LED desk lamp with dimmable light
... A23: PROD022 | B23: Backpack | C23: Fashion | D23: 60 | E23: Waterproof backpack with laptop compartment

Sheet Region Master
A1: Region | B1: Sales Target
A2: Central | B2: 97500
A3: East | B3: 50500
A4: North | B4: 105000
A5: South | B5: 91500
A6: West | B6: 90750

Sheet Customer Master
A1: Customer ID | B1: Customer Name | C1: Customer Type | D1: City | E1: State
A2: CUST001 | B2: James Miller | C2: Business | D2: New York | E2: New York
A3: CUST002 | B3: Emily Johnson | C3: Prime | D3: Seattle | E3: Washington
A4: CUST003 | B4: Ethan Davis | C4: Prime | D4: Austin | E4: Texas
A5: CUST004 | B5: Noah Wilson | C5: Prime | D5: San Francisco | E5: California
A6: CUST005 | B6: Olivia Martinez | C6: Prime | D6: Seattle | E6: Washington
A7: CUST006 | B7: Ava Robinson | C7: Prime | D7: Chicago | E7: Illinois
A8: CUST007 | B8: Liam Walker | C8: Prime | D8: San Francisco | E8: California
A9: CUST008 | B9: Harper Young | C9: Business | D9: Dallas | E9: Texas
A10: CUST009 | B10: Jackson Allen | C10: Business | D10: Seattle | E10: Washington
A11: CUST010 | B11: Charlotte Harris | C11: Prime | D11: Chicago | E11: Illinois
A12: CUST011 | B12: Mason Hall | C12: Business | D12: Miami | E12: Florida
... A50: CUST049 | B50: Hazel Gray | C50: Business | D50: Chicago | E50: Illinois
